[
  {
    "name": "CamB",
    "V_flat": 16.8,
    "R_max": 1.79,
    "gas_fraction": 0.37129018684476756,
    "bulge_fraction": 0.0,
    "mass_class": "dwarf",
    "sb_class": "LSB",
    "gas_class": "mixed",
    "bulge_class": "disk-dominated",
    "fit_class": "excellent",
    "rms_sigma": 4.9315828275586036,
    "rms_mond": 6.692140311899496,
    "wins_sigma": true,
    "mean_residual": -4.6240005877628985,
    "inner_residual": -4.5160414062015715,
    "outer_residual": -4.710367933011962,
    "residual_trend": 0.35436421288478687
  },
  {
    "name": "D564-8",
    "V_flat": 24.0,
    "R_max": 3.07,
    "gas_fraction": 0.5460820037674468,
    "bulge_fraction": 0.0,
    "mass_class": "dwarf",
    "sb_class": "LSB",
    "gas_class": "gas-rich",
    "bulge_class": "disk-dominated",
    "fit_class": "excellent",
    "rms_sigma": 2.692469871206999,
    "rms_mond": 5.384361985285578,
    "wins_sigma": true,
    "mean_residual": 2.557642481870253,
    "inner_residual": 2.2091085605227314,
    "outer_residual": 2.906176403217774,
    "residual_trend": 0.5922083299728261
  },
  {
    "name": "D631-7",
    "V_flat": 57.7,
    "R_max": 7.19,
    "gas_fraction": 0.6530187038229214,
    "bulge_fraction": 0.0,
    "mass_class": "dwarf",
    "sb_class": "LSB",
    "gas_class": "gas-rich",
    "bulge_class": "disk-dominated",
    "fit_class": "excellent",
    "rms_sigma": 6.455173840977273,
    "rms_mond": 16.018654325356444,
    "wins_sigma": true,
    "mean_residual": 3.4518464969754277,
    "inner_residual": -1.5563387842913117,
    "outer_residual": 8.460031778242167,
    "residual_trend": 2.530682786372766
  },
  {
    "name": "DDO064",
    "V_flat": 46.4,
    "R_max": 2.98,
    "gas_fraction": 0.720249578445482,
    "bulge_fraction": 0.0,
    "mass_class": "dwarf",
    "sb_class": "LSB",
    "gas_class": "gas-rich",
    "bulge_class": "disk-dominated",
    "fit_class": "excellent",
    "rms_sigma": 9.997778356689409,
    "rms_mond": 9.961427151225298,
    "wins_sigma": false,
    "mean_residual": 9.479701885862239,
    "inner_residual": 8.754017476898381,
    "outer_residual": 10.447281097814047,
    "residual_trend": 1.0188335264157473
  },
  {
    "name": "DDO154",
    "V_flat": 47.4,
    "R_max": 5.92,
    "gas_fraction": 0.7518836170933174,
    "bulge_fraction": 0.0,
    "mass_class": "dwarf",
    "sb_class": "LSB",
    "gas_class": "gas-rich",
    "bulge_class": "disk-dominated",
    "fit_class": "excellent",
    "rms_sigma": 6.917386037211659,
    "rms_mond": 13.596086810094398,
    "wins_sigma": true,
    "mean_residual": 6.580956970104228,
    "inner_residual": 6.165976147985694,
    "outer_residual": 6.8773718430460375,
    "residual_trend": 0.09266219133076344
  },
  {
    "name": "DDO161",
    "V_flat": 66.3,
    "R_max": 13.37,
    "gas_fraction": 0.767116233154854,
    "bulge_fraction": 0.0,
    "mass_class": "dwarf",
    "sb_class": "LSB",
    "gas_class": "gas-rich",
    "bulge_class": "disk-dominated",
    "fit_class": "good",
    "rms_sigma": 10.243100803922161,
    "rms_mond": 8.626478777147549,
    "wins_sigma": false,
    "mean_residual": -8.887055697262227,
    "inner_residual": -5.211683950095802,
    "outer_residual": -12.807452227573078,
    "residual_trend": -1.1358366697908042
  },
  {
    "name": "DDO168",
    "V_flat": 54.8,
    "R_max": 4.12,
    "gas_fraction": 0.7809356816448588,
    "bulge_fraction": 0.0,
    "mass_class": "dwarf",
    "sb_class": "LSB",
    "gas_class": "gas-rich",
    "bulge_class": "disk-dominated",
    "fit_class": "excellent",
    "rms_sigma": 7.709244600045331,
    "rms_mond": 11.344174294393165,
    "wins_sigma": true,
    "mean_residual": 6.218250423813234,
    "inner_residual": 1.4661683512556891,
    "outer_residual": 9.386305138851597,
    "residual_trend": 2.5226756575388474
  },
  {
    "name": "DDO170",
    "V_flat": 60.0,
    "R_max": 12.33,
    "gas_fraction": 0.7930359087775508,
    "bulge_fraction": 0.0,
    "mass_class": "dwarf",
    "sb_class": "LSB",
    "gas_class": "gas-rich",
    "bulge_class": "disk-dominated",
    "fit_class": "excellent",
    "rms_sigma": 8.69172207801811,
    "rms_mond": 11.624390560591863,
    "wins_sigma": true,
    "mean_residual": -5.187358575424374,
    "inner_residual": 2.9930567859046255,
    "outer_residual": -10.095607792221774,
    "residual_trend": -1.9133128680266525
  },
  {
    "name": "ESO079-G014",
    "V_flat": 177.0,
    "R_max": 16.67,
    "gas_fraction": 0.15556594165244197,
    "bulge_fraction": 0.0,
    "mass_class": "massive",
    "sb_class": "HSB",
    "gas_class": "gas-poor",
    "bulge_class": "disk-dominated",
    "fit_class": "good",
    "rms_sigma": 18.45488358004593,
    "rms_mond": 35.10529869525837,
    "wins_sigma": true,
    "mean_residual": 15.88569600096768,
    "inner_residual": 14.259933913914987,
    "outer_residual": 18.324339131546726,
    "residual_trend": 0.49711122341294717
  },
  {
    "name": "ESO116-G012",
    "V_flat": 111.0,
    "R_max": 9.86,
    "gas_fraction": 0.3641645661492476,
    "bulge_fraction": 0.0,
    "mass_class": "normal",
    "sb_class": "HSB",
    "gas_class": "mixed",
    "bulge_class": "disk-dominated",
    "fit_class": "good",
    "rms_sigma": 19.695080679396654,
    "rms_mond": 30.75755681240903,
    "wins_sigma": true,
    "mean_residual": 18.839846569226,
    "inner_residual": 16.566462175572482,
    "outer_residual": 21.438000161972884,
    "residual_trend": 0.9394466622215303
  },
  {
    "name": "ESO444-G084",
    "V_flat": 62.7,
    "R_max": 4.44,
    "gas_fraction": 0.7867908729021971,
    "bulge_fraction": 0.0,
    "mass_class": "dwarf",
    "sb_class": "LSB",
    "gas_class": "gas-rich",
    "bulge_class": "disk-dominated",
    "fit_class": "moderate",
    "rms_sigma": 21.57770532990484,
    "rms_mond": 24.38932180279413,
    "wins_sigma": true,
    "mean_residual": 20.879230710732884,
    "inner_residual": 17.485986005175036,
    "outer_residual": 25.403556984810013,
    "residual_trend": 3.4580076374807067
  },
  {
    "name": "ESO563-G021",
    "V_flat": 315.0,
    "R_max": 42.41,
    "gas_fraction": 0.09084514277495749,
    "bulge_fraction": 0.0,
    "mass_class": "massive",
    "sb_class": "HSB",
    "gas_class": "gas-poor",
    "bulge_class": "disk-dominated",
    "fit_class": "poor",
    "rms_sigma": 52.227625207416956,
    "rms_mond": 84.76192271102738,
    "wins_sigma": true,
    "mean_residual": 43.0950073484215,
    "inner_residual": 43.279984184637,
    "outer_residual": 42.8531145626012,
    "residual_trend": 0.4848632716783487
  },
  {
    "name": "F561-1",
    "V_flat": 50.4,
    "R_max": 9.66,
    "gas_fraction": 0.41194523766585883,
    "bulge_fraction": 0.0,
    "mass_class": "dwarf",
    "sb_class": "LSB",
    "gas_class": "mixed",
    "bulge_class": "disk-dominated",
    "fit_class": "moderate",
    "rms_sigma": 23.93032316842477,
    "rms_mond": 9.211181982058067,
    "wins_sigma": false,
    "mean_residual": -19.890778868237177,
    "inner_residual": -5.920701274988886,
    "outer_residual": -26.875817664861323,
    "residual_trend": -4.701674677864784
  },
  {
    "name": "F563-1",
    "V_flat": 111.0,
    "R_max": 20.1,
    "gas_fraction": 0.7407091141045202,
    "bulge_fraction": 0.0,
    "mass_class": "normal",
    "sb_class": "LSB",
    "gas_class": "gas-rich",
    "bulge_class": "disk-dominated",
    "fit_class": "moderate",
    "rms_sigma": 25.620570767757187,
    "rms_mond": 44.71328191167619,
    "wins_sigma": true,
    "mean_residual": 22.21842580617025,
    "inner_residual": 27.984276024442757,
    "outer_residual": 13.981496922923814,
    "residual_trend": -1.1581153963026523
  },
  {
    "name": "F563-V1",
    "V_flat": 28.6,
    "R_max": 7.87,
    "gas_fraction": 0.5818781572478374,
    "bulge_fraction": 0.0,
    "mass_class": "dwarf",
    "sb_class": "LSB",
    "gas_class": "gas-rich",
    "bulge_class": "disk-dominated",
    "fit_class": "moderate",
    "rms_sigma": 20.85045195626316,
    "rms_mond": 8.96368580230118,
    "wins_sigma": false,
    "mean_residual": -17.746560881233357,
    "inner_residual": -8.004767761707287,
    "outer_residual": -27.488354000759426,
    "residual_trend": -4.8717491677671925
  },
  {
    "name": "F563-V2",
    "V_flat": 118.0,
    "R_max": 10.47,
    "gas_fraction": 0.6066613593940643,
    "bulge_fraction": 0.0,
    "mass_class": "normal",
    "sb_class": "LSB",
    "gas_class": "gas-rich",
    "bulge_class": "disk-dominated",
    "fit_class": "poor",
    "rms_sigma": 33.49677780925518,
    "rms_mond": 43.96211086906193,
    "wins_sigma": true,
    "mean_residual": 30.37377481175661,
    "inner_residual": 33.84427409123843,
    "outer_residual": 25.168025892533887,
    "residual_trend": -0.3085654434328035
  },
  {
    "name": "F565-V2",
    "V_flat": 78.5,
    "R_max": 8.8,
    "gas_fraction": 0.7773262528222219,
    "bulge_fraction": 0.0,
    "mass_class": "dwarf",
    "sb_class": "LSB",
    "gas_class": "gas-rich",
    "bulge_class": "disk-dominated",
    "fit_class": "good",
    "rms_sigma": 15.068086942253075,
    "rms_mond": 27.570637200662787,
    "wins_sigma": true,
    "mean_residual": 14.331617775181014,
    "inner_residual": 11.60097120369277,
    "outer_residual": 16.379602703797197,
    "residual_trend": 0.798133315397921
  },
  {
    "name": "F567-2",
    "V_flat": 48.1,
    "R_max": 9.59,
    "gas_fraction": 0.5178577820987885,
    "bulge_fraction": 0.0,
    "mass_class": "dwarf",
    "sb_class": "LSB",
    "gas_class": "gas-rich",
    "bulge_class": "disk-dominated",
    "fit_class": "good",
    "rms_sigma": 13.87999069635816,
    "rms_mond": 8.427551712523028,
    "wins_sigma": false,
    "mean_residual": -7.188479328722318,
    "inner_residual": 4.568656339177082,
    "outer_residual": -15.026569773988584,
    "residual_trend": -4.008422530039077
  },
  {
    "name": "F568-1",
    "V_flat": 133.0,
    "R_max": 13.23,
    "gas_fraction": 0.6429906391805106,
    "bulge_fraction": 0.0,
    "mass_class": "normal",
    "sb_class": "LSB",
    "gas_class": "gas-rich",
    "bulge_class": "disk-dominated",
    "fit_class": "poor",
    "rms_sigma": 39.42186590042649,
    "rms_mond": 53.2742146918182,
    "wins_sigma": true,
    "mean_residual": 36.574463194775774,
    "inner_residual": 38.03512702895156,
    "outer_residual": 34.52953382692967,
    "residual_trend": 0.48654226330228845
  },
  {
    "name": "F568-3",
    "V_flat": 117.0,
    "R_max": 17.98,
    "gas_fraction": 0.529315951701816,
    "bulge_fraction": 0.0,
    "mass_class": "normal",
    "sb_class": "LSB",
    "gas_class": "gas-rich",
    "bulge_class": "disk-dominated",
    "fit_class": "good",
    "rms_sigma": 13.633951163676265,
    "rms_mond": 27.41792125135823,
    "wins_sigma": true,
    "mean_residual": 9.522929745579965,
    "inner_residual": 14.010528236245731,
    "outer_residual": 0.5477327642484345,
    "residual_trend": -0.8439046337068045
  },
  {
    "name": "F568-V1",
    "V_flat": 113.0,
    "R_max": 17.63,
    "gas_fraction": 0.5508568953356712,
    "bulge_fraction": 0.0,
    "mass_class": "normal",
    "sb_class": "LSB",
    "gas_class": "gas-rich",
    "bulge_class": "disk-dominated",
    "fit_class": "poor",
    "rms_sigma": 35.25086634476001,
    "rms_mond": 49.16688864008413,
    "wins_sigma": true,
    "mean_residual": 32.61459445472613,
    "inner_residual": 37.091706858515856,
    "outer_residual": 20.302535344304395,
    "residual_trend": -0.970001097391186
  },
  {
    "name": "F571-8",
    "V_flat": 140.0,
    "R_max": 15.55,
    "gas_fraction": 0.02081738200565025,
    "bulge_fraction": 0.0,
    "mass_class": "normal",
    "sb_class": "HSB",
    "gas_class": "gas-poor",
    "bulge_class": "disk-dominated",
    "fit_class": "moderate",
    "rms_sigma": 26.839296246171227,
    "rms_mond": 42.13034439578918,
    "wins_sigma": true,
    "mean_residual": 9.750358991966047,
    "inner_residual": 0.08259128664144413,
    "outer_residual": 41.976251343048055,
    "residual_trend": 5.325587472740503
  },
  {
    "name": "F571-V1",
    "V_flat": 83.9,
    "R_max": 13.59,
    "gas_fraction": 0.6000853231452132,
    "bulge_fraction": 0.0,
    "mass_class": "normal",
    "sb_class": "LSB",
    "gas_class": "gas-rich",
    "bulge_class": "disk-dominated",
    "fit_class": "excellent",
    "rms_sigma": 5.244781197324863,
    "rms_mond": 22.25803277323753,
    "wins_sigma": true,
    "mean_residual": 2.7432174075680593,
    "inner_residual": 6.512776029033133,
    "outer_residual": -0.08395155853074598,
    "residual_trend": -0.8754561758018664
  },
  {
    "name": "F574-1",
    "V_flat": 99.5,
    "R_max": 12.6,
    "gas_fraction": 0.4123672413266103,
    "bulge_fraction": 0.0,
    "mass_class": "normal",
    "sb_class": "LSB",
    "gas_class": "mixed",
    "bulge_class": "disk-dominated",
    "fit_class": "good",
    "rms_sigma": 17.097607840107713,
    "rms_mond": 31.44053694867693,
    "wins_sigma": true,
    "mean_residual": 14.486225628955655,
    "inner_residual": 19.26953769999992,
    "outer_residual": 9.702913557911396,
    "residual_trend": -1.1398002972357253
  },
  {
    "name": "F574-2",
    "V_flat": 36.0,
    "R_max": 10.83,
    "gas_fraction": 0.5461000092146547,
    "bulge_fraction": 0.0,
    "mass_class": "dwarf",
    "sb_class": "LSB",
    "gas_class": "gas-rich",
    "bulge_class": "disk-dominated",
    "fit_class": "poor",
    "rms_sigma": 31.244839491151378,
    "rms_mond": 13.913700539488513,
    "wins_sigma": false,
    "mean_residual": -28.31899247384764,
    "inner_residual": -13.390543429360665,
    "outer_residual": -38.271291836838955,
    "residual_trend": -4.26607997179383
  },
  {
    "name": "F579-V1",
    "V_flat": 114.0,
    "R_max": 15.16,
    "gas_fraction": 0.2865428140689522,
    "bulge_fraction": 0.0,
    "mass_class": "normal",
    "sb_class": "LSB",
    "gas_class": "mixed",
    "bulge_class": "disk-dominated",
    "fit_class": "moderate",
    "rms_sigma": 28.754689354531486,
    "rms_mond": 38.18620670757743,
    "wins_sigma": true,
    "mean_residual": 23.489005442897792,
    "inner_residual": 33.492720358376296,
    "outer_residual": 5.482318595036483,
    "residual_trend": -3.5773519405219463
  },
  {
    "name": "F583-1",
    "V_flat": 85.8,
    "R_max": 16.26,
    "gas_fraction": 0.8203987130323892,
    "bulge_fraction": 0.0,
    "mass_class": "normal",
    "sb_class": "LSB",
    "gas_class": "gas-rich",
    "bulge_class": "disk-dominated",
    "fit_class": "good",
    "rms_sigma": 16.93732392549488,
    "rms_mond": 25.614483583111426,
    "wins_sigma": true,
    "mean_residual": 12.682007381305171,
    "inner_residual": 15.666226744779305,
    "outer_residual": -9.202267950838467,
    "residual_trend": -1.2506178982290042
  },
  {
    "name": "F583-4",
    "V_flat": 67.2,
    "R_max": 7.29,
    "gas_fraction": 0.23395485150975054,
    "bulge_fraction": 0.0,
    "mass_class": "dwarf",
    "sb_class": "LSB",
    "gas_class": "mixed",
    "bulge_class": "disk-dominated",
    "fit_class": "excellent",
    "rms_sigma": 6.599558757261419,
    "rms_mond": 15.048655125304874,
    "wins_sigma": true,
    "mean_residual": 5.914366979638661,
    "inner_residual": 9.188984604304366,
    "outer_residual": 4.277058167305809,
    "residual_trend": -0.9465539974585097
  },
  {
    "name": "IC2574",
    "V_flat": 67.1,
    "R_max": 10.23,
    "gas_fraction": 0.6630728348703123,
    "bulge_fraction": 0.0,
    "mass_class": "dwarf",
    "sb_class": "LSB",
    "gas_class": "gas-rich",
    "bulge_class": "disk-dominated",
    "fit_class": "excellent",
    "rms_sigma": 5.462647604301203,
    "rms_mond": 10.100509302592545,
    "wins_sigma": true,
    "mean_residual": -4.136233114238925,
    "inner_residual": -0.7604102358996706,
    "outer_residual": -6.801356439243598,
    "residual_trend": -1.0206211447039313
  },
  {
    "name": "IC4202",
    "V_flat": 243.0,
    "R_max": 25.9,
    "gas_fraction": 0.07692712524505659,
    "bulge_fraction": 0.4494289463605429,
    "mass_class": "massive",
    "sb_class": "HSB",
    "gas_class": "gas-poor",
    "bulge_class": "bulge-dominated",
    "fit_class": "moderate",
    "rms_sigma": 29.512521413137275,
    "rms_mond": 44.34884540455988,
    "wins_sigma": true,
    "mean_residual": 10.189218463671802,
    "inner_residual": 10.20262243347567,
    "outer_residual": 10.175814493867934,
    "residual_trend": 0.7147531272311655
  },
  {
    "name": "KK98-251",
    "V_flat": 34.2,
    "R_max": 3.13,
    "gas_fraction": 0.795923282259187,
    "bulge_fraction": 0.0,
    "mass_class": "dwarf",
    "sb_class": "LSB",
    "gas_class": "gas-rich",
    "bulge_class": "disk-dominated",
    "fit_class": "excellent",
    "rms_sigma": 1.1996819255699687,
    "rms_mond": 2.027098349690347,
    "wins_sigma": true,
    "mean_residual": 0.5991013978614983,
    "inner_residual": 0.8038804368405261,
    "outer_residual": 0.36506821045689514,
    "residual_trend": -0.6560099034472056
  },
  {
    "name": "NGC0024",
    "V_flat": 109.0,
    "R_max": 11.27,
    "gas_fraction": 0.2216581578384344,
    "bulge_fraction": 0.0,
    "mass_class": "normal",
    "sb_class": "HSB",
    "gas_class": "mixed",
    "bulge_class": "disk-dominated",
    "fit_class": "poor",
    "rms_sigma": 34.264763034040435,
    "rms_mond": 35.63246911322096,
    "wins_sigma": true,
    "mean_residual": 32.76090714419904,
    "inner_residual": 34.07250544596212,
    "outer_residual": 24.563417758179778,
    "residual_trend": -0.3900252767593397
  },
  {
    "name": "NGC0055",
    "V_flat": 86.5,
    "R_max": 13.5,
    "gas_fraction": 0.5867106819790358,
    "bulge_fraction": 0.0,
    "mass_class": "normal",
    "sb_class": "LSB",
    "gas_class": "gas-rich",
    "bulge_class": "disk-dominated",
    "fit_class": "excellent",
    "rms_sigma": 9.206153020970154,
    "rms_mond": 11.406409180220317,
    "wins_sigma": true,
    "mean_residual": -7.521228851010534,
    "inner_residual": -3.0386122580366752,
    "outer_residual": -10.883191295740927,
    "residual_trend": -1.3371137450353452
  },
  {
    "name": "NGC0100",
    "V_flat": 90.4,
    "R_max": 9.62,
    "gas_fraction": 0.23559387488122907,
    "bulge_fraction": 0.0,
    "mass_class": "normal",
    "sb_class": "LSB",
    "gas_class": "mixed",
    "bulge_class": "disk-dominated",
    "fit_class": "excellent",
    "rms_sigma": 9.243245710443922,
    "rms_mond": 22.411195498290503,
    "wins_sigma": true,
    "mean_residual": 8.469895802482752,
    "inner_residual": 6.368957316381943,
    "outer_residual": 10.780928137193644,
    "residual_trend": 1.0740462100212047
  },
  {
    "name": "NGC0247",
    "V_flat": 107.0,
    "R_max": 14.54,
    "gas_fraction": 0.47108215618690014,
    "bulge_fraction": 0.0,
    "mass_class": "normal",
    "sb_class": "LSB",
    "gas_class": "mixed",
    "bulge_class": "disk-dominated",
    "fit_class": "excellent",
    "rms_sigma": 9.929923025126321,
    "rms_mond": 24.947351422558697,
    "wins_sigma": true,
    "mean_residual": 6.217243344026904,
    "inner_residual": 13.16107189983506,
    "outer_residual": 0.2653902961913417,
    "residual_trend": -1.7817794625789072
  },
  {
    "name": "NGC0289",
    "V_flat": 165.0,
    "R_max": 71.12,
    "gas_fraction": 0.15529911357018947,
    "bulge_fraction": 0.0,
    "mass_class": "massive",
    "sb_class": "LSB",
    "gas_class": "gas-poor",
    "bulge_class": "disk-dominated",
    "fit_class": "poor",
    "rms_sigma": 31.226519233724176,
    "rms_mond": 35.69395233915383,
    "wins_sigma": true,
    "mean_residual": -17.748208799076814,
    "inner_residual": -0.5330742113068698,
    "outer_residual": -40.70172158277007,
    "residual_trend": -1.068238380860472
  },
  {
    "name": "NGC0300",
    "V_flat": 92.8,
    "R_max": 11.8,
    "gas_fraction": 0.3832063769178972,
    "bulge_fraction": 0.0,
    "mass_class": "normal",
    "sb_class": "LSB",
    "gas_class": "mixed",
    "bulge_class": "disk-dominated",
    "fit_class": "good",
    "rms_sigma": 14.664456457402274,
    "rms_mond": 29.630464081905572,
    "wins_sigma": true,
    "mean_residual": 13.943676355481218,
    "inner_residual": 16.654225842770856,
    "outer_residual": 11.813958901182222,
    "residual_trend": -0.48090946783464766
  },
  {
    "name": "NGC0801",
    "V_flat": 216.0,
    "R_max": 59.82,
    "gas_fraction": 0.10144210223645166,
    "bulge_fraction": 0.0,
    "mass_class": "massive",
    "sb_class": "HSB",
    "gas_class": "gas-poor",
    "bulge_class": "disk-dominated",
    "fit_class": "poor",
    "rms_sigma": 40.85460278239327,
    "rms_mond": 22.25311401029521,
    "wins_sigma": false,
    "mean_residual": -18.235279331683916,
    "inner_residual": 5.964633745812648,
    "outer_residual": -56.955140255678415,
    "residual_trend": -1.598450287578131
  },
  {
    "name": "NGC0891",
    "V_flat": 210.0,
    "R_max": 17.11,
    "gas_fraction": 0.02414481620196627,
    "bulge_fraction": 0.45155634221284285,
    "mass_class": "massive",
    "sb_class": "HSB",
    "gas_class": "gas-poor",
    "bulge_class": "bulge-dominated",
    "fit_class": "moderate",
    "rms_sigma": 22.062357179774494,
    "rms_mond": 28.12920759815523,
    "wins_sigma": true,
    "mean_residual": -8.742284372515204,
    "inner_residual": -22.213761394768035,
    "outer_residual": 2.0348972452870613,
    "residual_trend": 2.304707504061303
  },
  {
    "name": "NGC1003",
    "V_flat": 113.0,
    "R_max": 30.24,
    "gas_fraction": 0.30701459008442716,
    "bulge_fraction": 0.0,
    "mass_class": "normal",
    "sb_class": "LSB",
    "gas_class": "mixed",
    "bulge_class": "disk-dominated",
    "fit_class": "excellent",
    "rms_sigma": 5.182906652986099,
    "rms_mond": 33.8945606341699,
    "wins_sigma": true,
    "mean_residual": -1.4674958386424983,
    "inner_residual": -0.027735326229812576,
    "outer_residual": -2.7557026129064806,
    "residual_trend": -0.25549755288813614
  },
  {
    "name": "NGC1090",
    "V_flat": 162.0,
    "R_max": 30.09,
    "gas_fraction": 0.15741874216356172,
    "bulge_fraction": 0.0,
    "mass_class": "massive",
    "sb_class": "HSB",
    "gas_class": "gas-poor",
    "bulge_class": "disk-dominated",
    "fit_class": "good",
    "rms_sigma": 18.495768083627937,
    "rms_mond": 25.147498371814613,
    "wins_sigma": true,
    "mean_residual": -9.364202736211631,
    "inner_residual": 3.301995509656639,
    "outer_residual": -22.0304009820799,
    "residual_trend": -1.3160853634558978
  },
  {
    "name": "NGC1705",
    "V_flat": 71.5,
    "R_max": 6.0,
    "gas_fraction": 0.23072941698399196,
    "bulge_fraction": 0.0,
    "mass_class": "dwarf",
    "sb_class": "HSB",
    "gas_class": "mixed",
    "bulge_class": "disk-dominated",
    "fit_class": "moderate",
    "rms_sigma": 28.744847444173423,
    "rms_mond": 33.719842389152724,
    "wins_sigma": true,
    "mean_residual": 28.615250031623027,
    "inner_residual": 29.947685522756522,
    "outer_residual": 27.282814540489532,
    "residual_trend": -0.6557660529724864
  },
  {
    "name": "NGC2366",
    "V_flat": 49.4,
    "R_max": 6.06,
    "gas_fraction": 0.723571053363048,
    "bulge_fraction": 0.0,
    "mass_class": "dwarf",
    "sb_class": "LSB",
    "gas_class": "gas-rich",
    "bulge_class": "disk-dominated",
    "fit_class": "excellent",
    "rms_sigma": 4.818560145263937,
    "rms_mond": 7.53460606015221,
    "wins_sigma": true,
    "mean_residual": 1.0090822675175002,
    "inner_residual": 3.52688055648615,
    "outer_residual": -1.50871602145115,
    "residual_trend": -1.6125665103603695
  },
  {
    "name": "NGC2403",
    "V_flat": 135.0,
    "R_max": 20.87,
    "gas_fraction": 0.27902743599374774,
    "bulge_fraction": 0.0,
    "mass_class": "normal",
    "sb_class": "HSB",
    "gas_class": "mixed",
    "bulge_class": "disk-dominated",
    "fit_class": "good",
    "rms_sigma": 15.820174212785624,
    "rms_mond": 31.853297496903487,
    "wins_sigma": true,
    "mean_residual": 15.167800399902427,
    "inner_residual": 16.94112231883325,
    "outer_residual": 10.776717553026094,
    "residual_trend": -0.36733690616647846
  },
  {
    "name": "NGC2683",
    "V_flat": 155.0,
    "R_max": 34.62,
    "gas_fraction": 0.020445323603597822,
    "bulge_fraction": 0.17249549822395097,
    "mass_class": "massive",
    "sb_class": "LSB",
    "gas_class": "gas-poor",
    "bulge_class": "intermediate",
    "fit_class": "moderate",
    "rms_sigma": 20.236774003781544,
    "rms_mond": 33.73911686182577,
    "wins_sigma": true,
    "mean_residual": -1.7814077815834977,
    "inner_residual": 15.224795147326251,
    "outer_residual": -15.953243555674954,
    "residual_trend": -1.787462538626317
  },
  {
    "name": "NGC2841",
    "V_flat": 289.0,
    "R_max": 63.64,
    "gas_fraction": 0.06334250308410355,
    "bulge_fraction": 0.5345125624108789,
    "mass_class": "massive",
    "sb_class": "HSB",
    "gas_class": "gas-poor",
    "bulge_class": "bulge-dominated",
    "fit_class": "poor",
    "rms_sigma": 64.80850529493462,
    "rms_mond": 96.76293576287517,
    "wins_sigma": true,
    "mean_residual": 60.962639117706516,
    "inner_residual": 74.05867178648249,
    "outer_residual": 33.13356969655757,
    "residual_trend": -1.0445171973239824
  },
  {
    "name": "NGC2903",
    "V_flat": 180.0,
    "R_max": 24.96,
    "gas_fraction": 0.030764156960426094,
    "bulge_fraction": 0.0,
    "mass_class": "massive",
    "sb_class": "HSB",
    "gas_class": "gas-poor",
    "bulge_class": "disk-dominated",
    "fit_class": "moderate",
    "rms_sigma": 24.149262073655002,
    "rms_mond": 39.57541949029398,
    "wins_sigma": true,
    "mean_residual": 1.035953679029574,
    "inner_residual": -2.215735828875715,
    "outer_residual": 5.6812244046085585,
    "residual_trend": 0.9058735275487382
  },
  {
    "name": "NGC2915",
    "V_flat": 86.1,
    "R_max": 10.04,
    "gas_fraction": 0.2489631199370918,
    "bulge_fraction": 0.0,
    "mass_class": "normal",
    "sb_class": "LSB",
    "gas_class": "mixed",
    "bulge_class": "disk-dominated",
    "fit_class": "moderate",
    "rms_sigma": 28.680465355716205,
    "rms_mond": 40.44076334724846,
    "wins_sigma": true,
    "mean_residual": 25.16564487724508,
    "inner_residual": 23.88818962605751,
    "outer_residual": 26.283418222034214,
    "residual_trend": 1.283816382191346
  },
  {
    "name": "NGC2955",
    "V_flat": 248.0,
    "R_max": 35.43,
    "gas_fraction": 0.07576657122945007,
    "bulge_fraction": 0.5281694030534893,
    "mass_class": "massive",
    "sb_class": "HSB",
    "gas_class": "gas-poor",
    "bulge_class": "bulge-dominated",
    "fit_class": "good",
    "rms_sigma": 17.215014462163523,
    "rms_mond": 19.953401281157884,
    "wins_sigma": true,
    "mean_residual": -1.2963456641458262,
    "inner_residual": 4.652839029420962,
    "outer_residual": -19.14389974484619,
    "residual_trend": -1.2270235826197742
  },
  {
    "name": "NGC2976",
    "V_flat": 85.3,
    "R_max": 2.27,
    "gas_fraction": 0.22049540403988274,
    "bulge_fraction": 0.0,
    "mass_class": "normal",
    "sb_class": "HSB",
    "gas_class": "mixed",
    "bulge_class": "disk-dominated",
    "fit_class": "excellent",
    "rms_sigma": 9.65783873167287,
    "rms_mond": 6.722189141634398,
    "wins_sigma": false,
    "mean_residual": 8.25829617131889,
    "inner_residual": 4.756978281006174,
    "outer_residual": 12.63494353420978,
    "residual_trend": 7.754687926469206
  },
  {
    "name": "NGC2998",
    "V_flat": 213.0,
    "R_max": 42.28,
    "gas_fraction": 0.1508565208863227,
    "bulge_fraction": 0.0,
    "mass_class": "massive",
    "sb_class": "HSB",
    "gas_class": "gas-poor",
    "bulge_class": "disk-dominated",
    "fit_class": "poor",
    "rms_sigma": 37.47668875782804,
    "rms_mond": 44.792850859421165,
    "wins_sigma": true,
    "mean_residual": 16.888913994464467,
    "inner_residual": 38.66584231776891,
    "outer_residual": -17.954171322822656,
    "residual_trend": -2.232789464912143
  },
  {
    "name": "NGC3109",
    "V_flat": 66.3,
    "R_max": 6.45,
    "gas_fraction": 0.7623951725292503,
    "bulge_fraction": 0.0,
    "mass_class": "dwarf",
    "sb_class": "LSB",
    "gas_class": "gas-rich",
    "bulge_class": "disk-dominated",
    "fit_class": "good",
    "rms_sigma": 13.45818331143452,
    "rms_mond": 21.401185958128625,
    "wins_sigma": true,
    "mean_residual": 12.718891621288208,
    "inner_residual": 9.138729731489619,
    "outer_residual": 16.02365644264075,
    "residual_trend": 2.1582207261025963
  },
  {
    "name": "NGC3198",
    "V_flat": 150.0,
    "R_max": 44.08,
    "gas_fraction": 0.1912006450978079,
    "bulge_fraction": 0.0,
    "mass_class": "massive",
    "sb_class": "HSB",
    "gas_class": "gas-poor",
    "bulge_class": "disk-dominated",
    "fit_class": "good",
    "rms_sigma": 15.183520375258457,
    "rms_mond": 30.83028398654403,
    "wins_sigma": true,
    "mean_residual": 0.5815208813012457,
    "inner_residual": 8.207496838195805,
    "outer_residual": -19.11891700734303,
    "residual_trend": -0.9129330948589792
  },
  {
    "name": "NGC3521",
    "V_flat": 206.0,
    "R_max": 17.74,
    "gas_fraction": 0.05015962413176992,
    "bulge_fraction": 0.0,
    "mass_class": "massive",
    "sb_class": "HSB",
    "gas_class": "gas-poor",
    "bulge_class": "disk-dominated",
    "fit_class": "good",
    "rms_sigma": 16.926365209082444,
    "rms_mond": 21.222007065021128,
    "wins_sigma": true,
    "mean_residual": 16.311777290901553,
    "inner_residual": 15.704177256270164,
    "outer_residual": 21.932077611241915,
    "residual_trend": 0.5893348592002338
  },
  {
    "name": "NGC3726",
    "V_flat": 168.0,
    "R_max": 32.52,
    "gas_fraction": 0.1446394240700629,
    "bulge_fraction": 0.0,
    "mass_class": "massive",
    "sb_class": "LSB",
    "gas_class": "gas-poor",
    "bulge_class": "disk-dominated",
    "fit_class": "good",
    "rms_sigma": 18.454766964505694,
    "rms_mond": 24.42737778353329,
    "wins_sigma": true,
    "mean_residual": -16.030696130971236,
    "inner_residual": -15.04445885670048,
    "outer_residual": -18.00317067951275,
    "residual_trend": -0.3051916803531447
  },
  {
    "name": "NGC3741",
    "V_flat": 50.2,
    "R_max": 7.0,
    "gas_fraction": 0.6660254872293421,
    "bulge_fraction": 0.0,
    "mass_class": "dwarf",
    "sb_class": "LSB",
    "gas_class": "gas-rich",
    "bulge_class": "disk-dominated",
    "fit_class": "good",
    "rms_sigma": 10.483705054313882,
    "rms_mond": 17.081369167624555,
    "wins_sigma": true,
    "mean_residual": 10.226001102751798,
    "inner_residual": 9.663149295957009,
    "outer_residual": 11.140635288793332,
    "residual_trend": 0.5549447858154805
  },
  {
    "name": "NGC3769",
    "V_flat": 118.0,
    "R_max": 37.16,
    "gas_fraction": 0.12837214715217599,
    "bulge_fraction": 0.0,
    "mass_class": "normal",
    "sb_class": "LSB",
    "gas_class": "gas-poor",
    "bulge_class": "disk-dominated",
    "fit_class": "good",
    "rms_sigma": 12.409615490948148,
    "rms_mond": 26.126842854042614,
    "wins_sigma": true,
    "mean_residual": -7.979635180172328,
    "inner_residual": -3.336257901832315,
    "outer_residual": -21.90976701519237,
    "residual_trend": -0.6859612409448743
  },
  {
    "name": "NGC3877",
    "V_flat": 170.0,
    "R_max": 11.35,
    "gas_fraction": 0.043130325131849306,
    "bulge_fraction": 0.0,
    "mass_class": "massive",
    "sb_class": "HSB",
    "gas_class": "gas-poor",
    "bulge_class": "disk-dominated",
    "fit_class": "moderate",
    "rms_sigma": 20.42092110844773,
    "rms_mond": 20.65464304069635,
    "wins_sigma": true,
    "mean_residual": 2.560536717579962,
    "inner_residual": 12.243396178162888,
    "outer_residual": -5.739057105776831,
    "residual_trend": -1.7109282376007768
  },
  {
    "name": "NGC3893",
    "V_flat": 176.0,
    "R_max": 19.05,
    "gas_fraction": 0.0943738479901966,
    "bulge_fraction": 0.0,
    "mass_class": "massive",
    "sb_class": "HSB",
    "gas_class": "gas-poor",
    "bulge_class": "disk-dominated",
    "fit_class": "good",
    "rms_sigma": 16.153078131120214,
    "rms_mond": 33.98259699429716,
    "wins_sigma": true,
    "mean_residual": 12.72274515438561,
    "inner_residual": 16.577051619748232,
    "outer_residual": 8.868438689022986,
    "residual_trend": -0.7079030686779069
  },
  {
    "name": "NGC3917",
    "V_flat": 137.0,
    "R_max": 14.86,
    "gas_fraction": 0.1532209455522495,
    "bulge_fraction": 0.0,
    "mass_class": "normal",
    "sb_class": "LSB",
    "gas_class": "gas-poor",
    "bulge_class": "disk-dominated",
    "fit_class": "good",
    "rms_sigma": 13.797021919415075,
    "rms_mond": 29.59965491432461,
    "wins_sigma": true,
    "mean_residual": 10.724043269041474,
    "inner_residual": 15.51112263758628,
    "outer_residual": 6.468861608112761,
    "residual_trend": -0.9066833109846291
  },
  {
    "name": "NGC3949",
    "V_flat": 165.0,
    "R_max": 7.07,
    "gas_fraction": 0.09804564141282576,
    "bulge_fraction": 0.0,
    "mass_class": "massive",
    "sb_class": "HSB",
    "gas_class": "gas-poor",
    "bulge_class": "disk-dominated",
    "fit_class": "good",
    "rms_sigma": 11.370473607052855,
    "rms_mond": 14.42711128101514,
    "wins_sigma": true,
    "mean_residual": 9.450538479475687,
    "inner_residual": 4.365828510379359,
    "outer_residual": 13.264070956297935,
    "residual_trend": 2.85371332840949
  },
  {
    "name": "NGC3953",
    "V_flat": 223.0,
    "R_max": 15.68,
    "gas_fraction": 0.04391172579318221,
    "bulge_fraction": 0.0,
    "mass_class": "massive",
    "sb_class": "HSB",
    "gas_class": "gas-poor",
    "bulge_class": "disk-dominated",
    "fit_class": "moderate",
    "rms_sigma": 20.727981352168534,
    "rms_mond": 26.967830871494208,
    "wins_sigma": true,
    "mean_residual": 16.366966258165746,
    "inner_residual": 30.41139379692599,
    "outer_residual": 7.940309734909602,
    "residual_trend": -3.035580181180731
  },
  {
    "name": "NGC3972",
    "V_flat": 134.0,
    "R_max": 8.72,
    "gas_fraction": 0.1418491545223212,
    "bulge_fraction": 0.0,
    "mass_class": "normal",
    "sb_class": "HSB",
    "gas_class": "gas-poor",
    "bulge_class": "disk-dominated",
    "fit_class": "good",
    "rms_sigma": 18.77947453790114,
    "rms_mond": 27.267455103899245,
    "wins_sigma": true,
    "mean_residual": 17.76933251818142,
    "inner_residual": 17.559976295390435,
    "outer_residual": 17.908903333375417,
    "residual_trend": 0.47129756399532285
  },
  {
    "name": "NGC3992",
    "V_flat": 241.0,
    "R_max": 46.02,
    "gas_fraction": 0.08253914323412273,
    "bulge_fraction": 0.0,
    "mass_class": "massive",
    "sb_class": "LSB",
    "gas_class": "gas-poor",
    "bulge_class": "disk-dominated",
    "fit_class": "moderate",
    "rms_sigma": 27.70172219917591,
    "rms_mond": 65.55929457483188,
    "wins_sigma": true,
    "mean_residual": 16.11869125328012,
    "inner_residual": 37.94110597299225,
    "outer_residual": -1.3392405224895867,
    "residual_trend": -1.8059088511375763
  },
  {
    "name": "NGC4010",
    "V_flat": 124.0,
    "R_max": 10.47,
    "gas_fraction": 0.21307756697466634,
    "bulge_fraction": 0.0,
    "mass_class": "normal",
    "sb_class": "HSB",
    "gas_class": "mixed",
    "bulge_class": "disk-dominated",
    "fit_class": "excellent",
    "rms_sigma": 7.957069175571526,
    "rms_mond": 19.278556925593374,
    "wins_sigma": true,
    "mean_residual": 4.6333260417936435,
    "inner_residual": 1.0521776449122384,
    "outer_residual": 7.191289182423219,
    "residual_trend": 0.3510597875874546
  },
  {
    "name": "NGC4013",
    "V_flat": 174.0,
    "R_max": 31.01,
    "gas_fraction": 0.035688773446173196,
    "bulge_fraction": 0.2684479516199637,
    "mass_class": "massive",
    "sb_class": "LSB",
    "gas_class": "gas-poor",
    "bulge_class": "intermediate",
    "fit_class": "good",
    "rms_sigma": 10.297551720100024,
    "rms_mond": 34.68604922840207,
    "wins_sigma": true,
    "mean_residual": -5.552336213831938,
    "inner_residual": 1.0468836886502524,
    "outer_residual": -9.751839788138787,
    "residual_trend": -0.5110833689230085
  },
  {
    "name": "NGC4051",
    "V_flat": 154.0,
    "R_max": 12.19,
    "gas_fraction": 0.07289964172389302,
    "bulge_fraction": 0.0,
    "mass_class": "massive",
    "sb_class": "HSB",
    "gas_class": "gas-poor",
    "bulge_class": "disk-dominated",
    "fit_class": "good",
    "rms_sigma": 14.352323847160866,
    "rms_mond": 7.608073484108638,
    "wins_sigma": false,
    "mean_residual": -6.388092048657356,
    "inner_residual": 4.481404887781447,
    "outer_residual": -14.540214750986458,
    "residual_trend": -2.9985141013849783
  },
  {
    "name": "NGC4068",
    "V_flat": 36.0,
    "R_max": 2.33,
    "gas_fraction": 0.5789893248276238,
    "bulge_fraction": 0.0,
    "mass_class": "dwarf",
    "sb_class": "HSB",
    "gas_class": "gas-rich",
    "bulge_class": "disk-dominated",
    "fit_class": "excellent",
    "rms_sigma": 2.0245295108673704,
    "rms_mond": 3.4645331029548645,
    "wins_sigma": true,
    "mean_residual": 0.7504404780168069,
    "inner_residual": -0.8779824192156355,
    "outer_residual": 2.3788633752492494,
    "residual_trend": 2.3486985443015733
  },
  {
    "name": "NGC4085",
    "V_flat": 133.0,
    "R_max": 6.2,
    "gas_fraction": 0.05215093050055466,
    "bulge_fraction": 0.0,
    "mass_class": "normal",
    "sb_class": "HSB",
    "gas_class": "gas-poor",
    "bulge_class": "disk-dominated",
    "fit_class": "good",
    "rms_sigma": 12.491648664278797,
    "rms_mond": 15.703792860339867,
    "wins_sigma": true,
    "mean_residual": -3.62628625784032,
    "inner_residual": -13.917362891388251,
    "outer_residual": 4.092021217320628,
    "residual_trend": 5.506764624513738
  },
  {
    "name": "NGC4088",
    "V_flat": 171.0,
    "R_max": 21.48,
    "gas_fraction": 0.07910121171906744,
    "bulge_fraction": 0.0,
    "mass_class": "massive",
    "sb_class": "HSB",
    "gas_class": "gas-poor",
    "bulge_class": "disk-dominated",
    "fit_class": "moderate",
    "rms_sigma": 28.578539523096154,
    "rms_mond": 16.647983146270413,
    "wins_sigma": false,
    "mean_residual": -26.935250529382802,
    "inner_residual": -20.441926144566484,
    "outer_residual": -33.42857491419913,
    "residual_trend": -1.0763467074358926
  },
  {
    "name": "NGC4100",
    "V_flat": 158.0,
    "R_max": 22.76,
    "gas_fraction": 0.06595254735552397,
    "bulge_fraction": 0.0,
    "mass_class": "massive",
    "sb_class": "LSB",
    "gas_class": "gas-poor",
    "bulge_class": "disk-dominated",
    "fit_class": "moderate",
    "rms_sigma": 20.841153153828586,
    "rms_mond": 39.33026895461673,
    "wins_sigma": true,
    "mean_residual": 14.076595021346973,
    "inner_residual": 27.307050256875563,
    "outer_residual": 2.8815944374381672,
    "residual_trend": -2.3689781529474843
  },
  {
    "name": "NGC4138",
    "V_flat": 147.0,
    "R_max": 18.58,
    "gas_fraction": 0.01831475952110357,
    "bulge_fraction": 0.3278982426267267,
    "mass_class": "normal",
    "sb_class": "HSB",
    "gas_class": "gas-poor",
    "bulge_class": "bulge-dominated",
    "fit_class": "good",
    "rms_sigma": 16.777247309765976,
    "rms_mond": 30.97760806452631,
    "wins_sigma": true,
    "mean_residual": 8.062676173305343,
    "inner_residual": 20.882732226303023,
    "outer_residual": -1.5523658664429192,
    "residual_trend": -1.7626959972483678
  },
  {
    "name": "NGC4157",
    "V_flat": 185.0,
    "R_max": 29.61,
    "gas_fraction": 0.07241197118721834,
    "bulge_fraction": 0.09257735976833507,
    "mass_class": "massive",
    "sb_class": "HSB",
    "gas_class": "gas-poor",
    "bulge_class": "disk-dominated",
    "fit_class": "good",
    "rms_sigma": 14.508953783625993,
    "rms_mond": 24.77773787129729,
    "wins_sigma": true,
    "mean_residual": -12.916865976238082,
    "inner_residual": -8.9143539139139,
    "outer_residual": -16.4746544760818,
    "residual_trend": -0.3978547173069288
  },
  {
    "name": "NGC4183",
    "V_flat": 112.0,
    "R_max": 21.02,
    "gas_fraction": 0.3511783464259932,
    "bulge_fraction": 0.0,
    "mass_class": "normal",
    "sb_class": "LSB",
    "gas_class": "mixed",
    "bulge_class": "disk-dominated",
    "fit_class": "good",
    "rms_sigma": 13.40026813496391,
    "rms_mond": 25.852994301911345,
    "wins_sigma": true,
    "mean_residual": 1.569304967835899,
    "inner_residual": 12.743175791780331,
    "outer_residual": -10.620372294648936,
    "residual_trend": -2.0633571297143134
  },
  {
    "name": "NGC4214",
    "V_flat": 80.6,
    "R_max": 5.63,
    "gas_fraction": 0.14914139725894077,
    "bulge_fraction": 0.0,
    "mass_class": "normal",
    "sb_class": "HSB",
    "gas_class": "gas-poor",
    "bulge_class": "disk-dominated",
    "fit_class": "moderate",
    "rms_sigma": 27.302655377798015,
    "rms_mond": 31.863496847872316,
    "wins_sigma": true,
    "mean_residual": 27.048859419512123,
    "inner_residual": 25.2810538789868,
    "outer_residual": 28.81666496003744,
    "residual_trend": 0.9160520381510745
  },
  {
    "name": "NGC4217",
    "V_flat": 177.0,
    "R_max": 16.72,
    "gas_fraction": 0.019133442771718415,
    "bulge_fraction": 0.8720120922591388,
    "mass_class": "massive",
    "sb_class": "HSB",
    "gas_class": "gas-poor",
    "bulge_class": "bulge-dominated",
    "fit_class": "poor",
    "rms_sigma": 42.39255132046463,
    "rms_mond": 44.039568185527806,
    "wins_sigma": true,
    "mean_residual": -31.96354460409209,
    "inner_residual": -54.554334786816156,
    "outer_residual": -11.631833439640413,
    "residual_trend": 4.842615244300493
  },
  {
    "name": "NGC4389",
    "V_flat": 95.9,
    "R_max": 5.32,
    "gas_fraction": 0.03965518974287091,
    "bulge_fraction": 0.0,
    "mass_class": "normal",
    "sb_class": "HSB",
    "gas_class": "gas-poor",
    "bulge_class": "disk-dominated",
    "fit_class": "poor",
    "rms_sigma": 31.607492878366006,
    "rms_mond": 33.64993645108864,
    "wins_sigma": true,
    "mean_residual": -30.751353637457964,
    "inner_residual": -35.80656663677079,
    "outer_residual": -28.223747137801546,
    "residual_trend": 3.8218869161975357
  },
  {
    "name": "NGC4559",
    "V_flat": 120.0,
    "R_max": 20.97,
    "gas_fraction": 0.28599996572784736,
    "bulge_fraction": 0.0,
    "mass_class": "normal",
    "sb_class": "LSB",
    "gas_class": "mixed",
    "bulge_class": "disk-dominated",
    "fit_class": "good",
    "rms_sigma": 13.496822278615088,
    "rms_mond": 16.020786118366523,
    "wins_sigma": true,
    "mean_residual": -9.751912925340822,
    "inner_residual": -2.8243546952778242,
    "outer_residual": -16.67947115540382,
    "residual_trend": -1.4780719797500002
  },
  {
    "name": "NGC5005",
    "V_flat": 264.0,
    "R_max": 11.47,
    "gas_fraction": 0.058170846814664404,
    "bulge_fraction": 0.5306773603706987,
    "mass_class": "massive",
    "sb_class": "HSB",
    "gas_class": "gas-poor",
    "bulge_class": "bulge-dominated",
    "fit_class": "good",
    "rms_sigma": 17.498569664845213,
    "rms_mond": 19.42827637494708,
    "wins_sigma": true,
    "mean_residual": 8.401425478982262,
    "inner_residual": -1.8457092672424267,
    "outer_residual": 21.210343911763122,
    "residual_trend": 3.9401894458981457
  },
  {
    "name": "NGC5033",
    "V_flat": 194.0,
    "R_max": 44.59,
    "gas_fraction": 0.03985514560619861,
    "bulge_fraction": 0.6300869118016542,
    "mass_class": "massive",
    "sb_class": "HSB",
    "gas_class": "gas-poor",
    "bulge_class": "bulge-dominated",
    "fit_class": "good",
    "rms_sigma": 18.722984211802892,
    "rms_mond": 48.904016534872845,
    "wins_sigma": true,
    "mean_residual": 1.6998906670516438,
    "inner_residual": 9.934083366158843,
    "outer_residual": -8.181140571876995,
    "residual_trend": -0.5016096602374043
  },
  {
    "name": "NGC5055",
    "V_flat": 174.0,
    "R_max": 54.59,
    "gas_fraction": 0.05363724688774986,
    "bulge_fraction": 0.0,
    "mass_class": "massive",
    "sb_class": "HSB",
    "gas_class": "gas-poor",
    "bulge_class": "disk-dominated",
    "fit_class": "moderate",
    "rms_sigma": 26.390052114487254,
    "rms_mond": 23.802847242950516,
    "wins_sigma": false,
    "mean_residual": -22.549697391867614,
    "inner_residual": -13.079420579706703,
    "outer_residual": -39.59619565375725,
    "residual_trend": -0.7713205982041694
  },
  {
    "name": "NGC5371",
    "V_flat": 209.0,
    "R_max": 46.24,
    "gas_fraction": 0.06921394057414808,
    "bulge_fraction": 0.0,
    "mass_class": "massive",
    "sb_class": "HSB",
    "gas_class": "gas-poor",
    "bulge_class": "disk-dominated",
    "fit_class": "poor",
    "rms_sigma": 45.80700042641828,
    "rms_mond": 19.834528304240308,
    "wins_sigma": false,
    "mean_residual": -22.15601195517044,
    "inner_residual": 9.995747919768217,
    "outer_residual": -57.88018959399116,
    "residual_trend": -2.6073050287967603
  },
  {
    "name": "NGC5585",
    "V_flat": 89.6,
    "R_max": 10.96,
    "gas_fraction": 0.38835752229965825,
    "bulge_fraction": 0.0,
    "mass_class": "normal",
    "sb_class": "HSB",
    "gas_class": "mixed",
    "bulge_class": "disk-dominated",
    "fit_class": "excellent",
    "rms_sigma": 6.673143911601073,
    "rms_mond": 17.978129595359768,
    "wins_sigma": true,
    "mean_residual": 5.104129385606594,
    "inner_residual": 4.0743365121255195,
    "outer_residual": 6.820450841408384,
    "residual_trend": 0.31995160226216823
  },
  {
    "name": "NGC5907",
    "V_flat": 215.0,
    "R_max": 50.33,
    "gas_fraction": 0.13473163826865128,
    "bulge_fraction": 0.0,
    "mass_class": "massive",
    "sb_class": "LSB",
    "gas_class": "gas-poor",
    "bulge_class": "disk-dominated",
    "fit_class": "moderate",
    "rms_sigma": 27.9723803479222,
    "rms_mond": 48.01402592966329,
    "wins_sigma": true,
    "mean_residual": -2.3614804417874256,
    "inner_residual": 20.476720339037698,
    "outer_residual": -22.915861144530034,
    "residual_trend": -1.8255369070879732
  },
  {
    "name": "NGC5985",
    "V_flat": 288.0,
    "R_max": 34.72,
    "gas_fraction": 0.06353178931860438,
    "bulge_fraction": 0.2425777380501954,
    "mass_class": "massive",
    "sb_class": "LSB",
    "gas_class": "gas-poor",
    "bulge_class": "intermediate",
    "fit_class": "poor",
    "rms_sigma": 81.89184183539041,
    "rms_mond": 105.99042194560788,
    "wins_sigma": true,
    "mean_residual": 77.84839787338795,
    "inner_residual": 96.09670974652903,
    "outer_residual": 53.08283175983935,
    "residual_trend": -2.863390723168457
  },
  {
    "name": "NGC6015",
    "V_flat": 152.0,
    "R_max": 29.23,
    "gas_fraction": 0.17263426907225168,
    "bulge_fraction": 0.0,
    "mass_class": "massive",
    "sb_class": "HSB",
    "gas_class": "gas-poor",
    "bulge_class": "disk-dominated",
    "fit_class": "moderate",
    "rms_sigma": 20.750881795152093,
    "rms_mond": 40.677868121531915,
    "wins_sigma": true,
    "mean_residual": 14.594262905116018,
    "inner_residual": 22.541926649873727,
    "outer_residual": 3.1143041626882075,
    "residual_trend": -1.2996783958378924
  },
  {
    "name": "NGC6195",
    "V_flat": 246.0,
    "R_max": 36.43,
    "gas_fraction": 0.05937540249202561,
    "bulge_fraction": 0.5796602409324508,
    "mass_class": "massive",
    "sb_class": "HSB",
    "gas_class": "gas-poor",
    "bulge_class": "bulge-dominated",
    "fit_class": "moderate",
    "rms_sigma": 22.85911478158035,
    "rms_mond": 12.49748992105105,
    "wins_sigma": false,
    "mean_residual": -17.575118192822003,
    "inner_residual": -11.797349137697413,
    "outer_residual": -33.94546384900834,
    "residual_trend": -1.2240265559786465
  },
  {
    "name": "NGC6503",
    "V_flat": 115.0,
    "R_max": 23.5,
    "gas_fraction": 0.07509611446870737,
    "bulge_fraction": 0.0,
    "mass_class": "normal",
    "sb_class": "LSB",
    "gas_class": "gas-poor",
    "bulge_class": "disk-dominated",
    "fit_class": "excellent",
    "rms_sigma": 9.312835504152616,
    "rms_mond": 33.845781707240434,
    "wins_sigma": true,
    "mean_residual": 5.920079815011649,
    "inner_residual": 11.912285879948039,
    "outer_residual": 0.30238662913378267,
    "residual_trend": -0.9112935840350807
  },
  {
    "name": "NGC6674",
    "V_flat": 242.0,
    "R_max": 72.41,
    "gas_fraction": 0.05141418285694829,
    "bulge_fraction": 0.4072910790518758,
    "mass_class": "massive",
    "sb_class": "LSB",
    "gas_class": "gas-poor",
    "bulge_class": "bulge-dominated",
    "fit_class": "poor",
    "rms_sigma": 33.64596490162222,
    "rms_mond": 76.98632291655562,
    "wins_sigma": true,
    "mean_residual": 15.404100683796406,
    "inner_residual": 40.63021305702142,
    "outer_residual": -6.668747642775486,
    "residual_trend": -1.124454307032091
  },
  {
    "name": "NGC6946",
    "V_flat": 155.0,
    "R_max": 20.4,
    "gas_fraction": 0.03536910449019799,
    "bulge_fraction": 0.621729313938242,
    "mass_class": "massive",
    "sb_class": "HSB",
    "gas_class": "gas-poor",
    "bulge_class": "bulge-dominated",
    "fit_class": "good",
    "rms_sigma": 11.352545966033583,
    "rms_mond": 18.381869582476774,
    "wins_sigma": true,
    "mean_residual": -4.845119798557938,
    "inner_residual": 0.8421626476815393,
    "outer_residual": -10.532402244797419,
    "residual_trend": -0.9320743894512084
  },
  {
    "name": "NGC7331",
    "V_flat": 238.0,
    "R_max": 36.31,
    "gas_fraction": 0.04836298473234492,
    "bulge_fraction": 0.15209334911123362,
    "mass_class": "massive",
    "sb_class": "HSB",
    "gas_class": "gas-poor",
    "bulge_class": "intermediate",
    "fit_class": "good",
    "rms_sigma": 17.177163936215376,
    "rms_mond": 31.153199395957273,
    "wins_sigma": true,
    "mean_residual": -15.33120640656285,
    "inner_residual": -16.100058701388143,
    "outer_residual": -14.471900900581645,
    "residual_trend": 0.2656897660399558
  },
  {
    "name": "NGC7793",
    "V_flat": 94.5,
    "R_max": 7.87,
    "gas_fraction": 0.20546535767081073,
    "bulge_fraction": 0.0,
    "mass_class": "normal",
    "sb_class": "HSB",
    "gas_class": "mixed",
    "bulge_class": "disk-dominated",
    "fit_class": "good",
    "rms_sigma": 13.83641665373253,
    "rms_mond": 14.933381134358227,
    "wins_sigma": true,
    "mean_residual": 11.445277569495397,
    "inner_residual": 11.206066604712687,
    "outer_residual": 12.306437042713146,
    "residual_trend": 0.37817922429603673
  },
  {
    "name": "NGC7814",
    "V_flat": 214.0,
    "R_max": 19.53,
    "gas_fraction": 0.006002586507771901,
    "bulge_fraction": 0.9114086571538981,
    "mass_class": "massive",
    "sb_class": "HSB",
    "gas_class": "gas-poor",
    "bulge_class": "bulge-dominated",
    "fit_class": "moderate",
    "rms_sigma": 29.61142590845148,
    "rms_mond": 49.509558808444105,
    "wins_sigma": true,
    "mean_residual": 24.455343728716123,
    "inner_residual": 17.974281620958262,
    "outer_residual": 30.936405836473984,
    "residual_trend": 1.8017536351652308
  },
  {
    "name": "PGC51017",
    "V_flat": 18.3,
    "R_max": 3.63,
    "gas_fraction": 0.4988021599093329,
    "bulge_fraction": 0.0,
    "mass_class": "dwarf",
    "sb_class": "LSB",
    "gas_class": "mixed",
    "bulge_class": "disk-dominated",
    "fit_class": "good",
    "rms_sigma": 11.878343112300419,
    "rms_mond": 8.505534643239729,
    "wins_sigma": false,
    "mean_residual": -7.445255478209482,
    "inner_residual": -0.17377040120356332,
    "outer_residual": -14.716740555215402,
    "residual_trend": -7.7835898307526135
  },
  {
    "name": "UGC00128",
    "V_flat": 129.0,
    "R_max": 53.75,
    "gas_fraction": 0.5495035345074164,
    "bulge_fraction": 0.0,
    "mass_class": "normal",
    "sb_class": "LSB",
    "gas_class": "gas-rich",
    "bulge_class": "disk-dominated",
    "fit_class": "good",
    "rms_sigma": 17.44383110604478,
    "rms_mond": 45.46488224069191,
    "wins_sigma": true,
    "mean_residual": -2.997875959090697,
    "inner_residual": 11.724307568233312,
    "outer_residual": -17.720059486414705,
    "residual_trend": -0.9673042886344755
  },
  {
    "name": "UGC00191",
    "V_flat": 81.0,
    "R_max": 9.98,
    "gas_fraction": 0.5685691772306786,
    "bulge_fraction": 0.0,
    "mass_class": "normal",
    "sb_class": "LSB",
    "gas_class": "gas-rich",
    "bulge_class": "disk-dominated",
    "fit_class": "good",
    "rms_sigma": 16.360513426633645,
    "rms_mond": 19.474371230083708,
    "wins_sigma": true,
    "mean_residual": 13.366953944840862,
    "inner_residual": 17.406570903357316,
    "outer_residual": -0.771705409966728,
    "residual_trend": -2.219704177831365
  },
  {
    "name": "UGC00731",
    "V_flat": 73.9,
    "R_max": 10.91,
    "gas_fraction": 0.9210079024396796,
    "bulge_fraction": 0.0,
    "mass_class": "dwarf",
    "sb_class": "LSB",
    "gas_class": "gas-rich",
    "bulge_class": "disk-dominated",
    "fit_class": "good",
    "rms_sigma": 16.3873493723701,
    "rms_mond": 24.397556615864694,
    "wins_sigma": true,
    "mean_residual": 10.082832737484102,
    "inner_residual": 21.590953281650297,
    "outer_residual": -1.4252878066821009,
    "residual_trend": -3.92774075474224
  },
  {
    "name": "UGC00891",
    "V_flat": 60.15,
    "R_max": 7.39,
    "gas_fraction": 0.7331406566467651,
    "bulge_fraction": 0.0,
    "mass_class": "dwarf",
    "sb_class": "LSB",
    "gas_class": "gas-rich",
    "bulge_class": "disk-dominated",
    "fit_class": "excellent",
    "rms_sigma": 4.556613851398934,
    "rms_mond": 15.783783188689831,
    "wins_sigma": true,
    "mean_residual": 4.086686702394013,
    "inner_residual": 2.343724470564249,
    "outer_residual": 5.248661523613857,
    "residual_trend": 0.8668245829177884
  },
  {
    "name": "UGC01230",
    "V_flat": 103.0,
    "R_max": 36.54,
    "gas_fraction": 0.607597101995845,
    "bulge_fraction": 0.0,
    "mass_class": "normal",
    "sb_class": "LSB",
    "gas_class": "gas-rich",
    "bulge_class": "disk-dominated",
    "fit_class": "moderate",
    "rms_sigma": 25.476244778838783,
    "rms_mond": 32.482941339860396,
    "wins_sigma": true,
    "mean_residual": 2.2651458406974894,
    "inner_residual": 16.188941310914934,
    "outer_residual": -34.864975413215696,
    "residual_trend": -1.8918918881376048
  },
  {
    "name": "UGC01281",
    "V_flat": 56.4,
    "R_max": 4.99,
    "gas_fraction": 0.6762578677821651,
    "bulge_fraction": 0.0,
    "mass_class": "dwarf",
    "sb_class": "LSB",
    "gas_class": "gas-rich",
    "bulge_class": "disk-dominated",
    "fit_class": "good",
    "rms_sigma": 10.039117856135801,
    "rms_mond": 13.651537935878757,
    "wins_sigma": true,
    "mean_residual": 9.55301129795464,
    "inner_residual": 8.129376410478548,
    "outer_residual": 11.767554456250785,
    "residual_trend": 1.3843834690922885
  },
  {
    "name": "UGC02023",
    "V_flat": 47.9,
    "R_max": 3.78,
    "gas_fraction": 0.35914617433586377,
    "bulge_fraction": 0.0,
    "mass_class": "dwarf",
    "sb_class": "LSB",
    "gas_class": "mixed",
    "bulge_class": "disk-dominated",
    "fit_class": "excellent",
    "rms_sigma": 3.3413227291192085,
    "rms_mond": 6.684392546009964,
    "wins_sigma": true,
    "mean_residual": -0.1809776765803896,
    "inner_residual": -2.1401151335076367,
    "outer_residual": 1.1251139613711085,
    "residual_trend": 2.278352063955842
  },
  {
    "name": "UGC02259",
    "V_flat": 88.3,
    "R_max": 8.14,
    "gas_fraction": 0.4441493663879547,
    "bulge_fraction": 0.0,
    "mass_class": "normal",
    "sb_class": "LSB",
    "gas_class": "mixed",
    "bulge_class": "disk-dominated",
    "fit_class": "moderate",
    "rms_sigma": 25.267995373209175,
    "rms_mond": 33.566984448731844,
    "wins_sigma": true,
    "mean_residual": 24.21496449920148,
    "inner_residual": 32.80703028083419,
    "outer_residual": 19.059725030221852,
    "residual_trend": -2.9912888747921422
  },
  {
    "name": "UGC02455",
    "V_flat": 53.1,
    "R_max": 4.03,
    "gas_fraction": 0.22553735535916178,
    "bulge_fraction": 0.0,
    "mass_class": "dwarf",
    "sb_class": "HSB",
    "gas_class": "mixed",
    "bulge_class": "disk-dominated",
    "fit_class": "moderate",
    "rms_sigma": 25.98509786389106,
    "rms_mond": 27.202962961952096,
    "wins_sigma": true,
    "mean_residual": -25.027909705101976,
    "inner_residual": -26.257552536733407,
    "outer_residual": -23.79826687347055,
    "residual_trend": 0.6063193373592087
  },
  {
    "name": "UGC02487",
    "V_flat": 332.0,
    "R_max": 80.38,
    "gas_fraction": 0.03108586422313934,
    "bulge_fraction": 0.4352654176444352,
    "mass_class": "massive",
    "sb_class": "LSB",
    "gas_class": "gas-poor",
    "bulge_class": "bulge-dominated",
    "fit_class": "poor",
    "rms_sigma": 66.38687085404644,
    "rms_mond": 121.18691031981916,
    "wins_sigma": true,
    "mean_residual": 60.013818856006765,
    "inner_residual": 87.51276560976953,
    "outer_residual": 35.57031063043987,
    "residual_trend": -1.1528163421338213
  },
  {
    "name": "UGC02885",
    "V_flat": 298.0,
    "R_max": 74.07,
    "gas_fraction": 0.08562626388047975,
    "bulge_fraction": 0.5692811239639002,
    "mass_class": "massive",
    "sb_class": "HSB",
    "gas_class": "gas-poor",
    "bulge_class": "bulge-dominated",
    "fit_class": "moderate",
    "rms_sigma": 22.17007692962186,
    "rms_mond": 68.70839867464157,
    "wins_sigma": true,
    "mean_residual": 5.6449887245634836,
    "inner_residual": 22.371704800142517,
    "outer_residual": -9.409055743457646,
    "residual_trend": -0.8314210123149438
  },
  {
    "name": "UGC02916",
    "V_flat": 182.0,
    "R_max": 38.0,
    "gas_fraction": 0.09327262026511453,
    "bulge_fraction": 0.8076047134261319,
    "mass_class": "massive",
    "sb_class": "HSB",
    "gas_class": "gas-poor",
    "bulge_class": "bulge-dominated",
    "fit_class": "moderate",
    "rms_sigma": 24.98243367945959,
    "rms_mond": 24.763471249421944,
    "wins_sigma": false,
    "mean_residual": -5.338065244329286,
    "inner_residual": 0.2759639840875738,
    "outer_residual": -34.210215561901705,
    "residual_trend": -1.3539672727658765
  },
  {
    "name": "UGC02953",
    "V_flat": 263.0,
    "R_max": 62.39,
    "gas_fraction": 0.012640829664851146,
    "bulge_fraction": 0.4898370083741419,
    "mass_class": "massive",
    "sb_class": "HSB",
    "gas_class": "gas-poor",
    "bulge_class": "bulge-dominated",
    "fit_class": "poor",
    "rms_sigma": 37.311607960254946,
    "rms_mond": 60.376525103713654,
    "wins_sigma": true,
    "mean_residual": 28.279941051385777,
    "inner_residual": 31.761868320037667,
    "outer_residual": 15.07763349108068,
    "residual_trend": -0.2532983012478699
  },
  {
    "name": "UGC03205",
    "V_flat": 220.0,
    "R_max": 40.04,
    "gas_fraction": 0.06467657142266883,
    "bulge_fraction": 0.44344447565911665,
    "mass_class": "massive",
    "sb_class": "HSB",
    "gas_class": "gas-poor",
    "bulge_class": "bulge-dominated",
    "fit_class": "poor",
    "rms_sigma": 33.904494277000026,
    "rms_mond": 47.4314756451299,
    "wins_sigma": true,
    "mean_residual": 27.604782323295364,
    "inner_residual": 31.680567289956304,
    "outer_residual": 3.7323275185669575,
    "residual_trend": -1.232573097105793
  },
  {
    "name": "UGC03546",
    "V_flat": 191.0,
    "R_max": 29.23,
    "gas_fraction": 0.009375881267294345,
    "bulge_fraction": 0.8136672717695662,
    "mass_class": "massive",
    "sb_class": "HSB",
    "gas_class": "gas-poor",
    "bulge_class": "bulge-dominated",
    "fit_class": "moderate",
    "rms_sigma": 26.78954789463502,
    "rms_mond": 36.07337924444704,
    "wins_sigma": true,
    "mean_residual": -15.403117034746355,
    "inner_residual": -19.766969586083906,
    "outer_residual": -3.402522518568084,
    "residual_trend": 1.519512765675424
  },
  {
    "name": "UGC03580",
    "V_flat": 127.0,
    "R_max": 27.06,
    "gas_fraction": 0.12178646525520735,
    "bulge_fraction": 0.5442274197465856,
    "mass_class": "normal",
    "sb_class": "HSB",
    "gas_class": "gas-poor",
    "bulge_class": "bulge-dominated",
    "fit_class": "good",
    "rms_sigma": 16.093172803338625,
    "rms_mond": 25.61076637823834,
    "wins_sigma": true,
    "mean_residual": -11.684307617401219,
    "inner_residual": -13.004077353404291,
    "outer_residual": -5.250430154386249,
    "residual_trend": 0.6963268285905974
  },
  {
    "name": "UGC04278",
    "V_flat": 91.3,
    "R_max": 6.69,
    "gas_fraction": 0.7086842752246452,
    "bulge_fraction": 0.0,
    "mass_class": "normal",
    "sb_class": "LSB",
    "gas_class": "gas-rich",
    "bulge_class": "disk-dominated",
    "fit_class": "good",
    "rms_sigma": 15.95361172053099,
    "rms_mond": 23.92346661061762,
    "wins_sigma": true,
    "mean_residual": 14.468618820357579,
    "inner_residual": 9.23120957987787,
    "outer_residual": 19.303150426954236,
    "residual_trend": 2.1841267542925333
  },
  {
    "name": "UGC04305",
    "V_flat": 34.6,
    "R_max": 5.52,
    "gas_fraction": 0.5616200102476493,
    "bulge_fraction": 0.0,
    "mass_class": "dwarf",
    "sb_class": "LSB",
    "gas_class": "gas-rich",
    "bulge_class": "disk-dominated",
    "fit_class": "good",
    "rms_sigma": 16.431550647270814,
    "rms_mond": 10.172560463237474,
    "wins_sigma": false,
    "mean_residual": -11.47139264726839,
    "inner_residual": 0.5462547623454068,
    "outer_residual": -21.486098821946555,
    "residual_trend": -6.860136955320148
  },
  {
    "name": "UGC04325",
    "V_flat": 91.6,
    "R_max": 5.59,
    "gas_fraction": 0.40537083035723803,
    "bulge_fraction": 0.0,
    "mass_class": "normal",
    "sb_class": "LSB",
    "gas_class": "mixed",
    "bulge_class": "disk-dominated",
    "fit_class": "moderate",
    "rms_sigma": 29.578415198020487,
    "rms_mond": 33.17579343015305,
    "wins_sigma": true,
    "mean_residual": 28.583584673850588,
    "inner_residual": 34.012964640581615,
    "outer_residual": 23.15420470711956,
    "residual_trend": -2.8883231677078425
  },
  {
    "name": "UGC04483",
    "V_flat": 24.2,
    "R_max": 1.21,
    "gas_fraction": 0.7552724478094595,
    "bulge_fraction": 0.0,
    "mass_class": "dwarf",
    "sb_class": "HSB",
    "gas_class": "gas-rich",
    "bulge_class": "disk-dominated",
    "fit_class": "excellent",
    "rms_sigma": 5.1169408708112885,
    "rms_mond": 3.0759442677112894,
    "wins_sigma": false,
    "mean_residual": 4.8318495168340725,
    "inner_residual": 4.187257632943661,
    "outer_residual": 5.476441400724483,
    "residual_trend": 2.8228797418327995
  },
  {
    "name": "UGC04499",
    "V_flat": 73.3,
    "R_max": 8.18,
    "gas_fraction": 0.5872276188957261,
    "bulge_fraction": 0.0,
    "mass_class": "dwarf",
    "sb_class": "LSB",
    "gas_class": "gas-rich",
    "bulge_class": "disk-dominated",
    "fit_class": "excellent",
    "rms_sigma": 6.348324165762839,
    "rms_mond": 13.9439342214931,
    "wins_sigma": true,
    "mean_residual": 3.574222606097234,
    "inner_residual": 7.224208890510567,
    "outer_residual": 0.654233578566567,
    "residual_trend": -1.5404939162048648
  },
  {
    "name": "UGC05005",
    "V_flat": 99.4,
    "R_max": 28.61,
    "gas_fraction": 0.606701016868269,
    "bulge_fraction": 0.0,
    "mass_class": "normal",
    "sb_class": "LSB",
    "gas_class": "gas-rich",
    "bulge_class": "disk-dominated",
    "fit_class": "good",
    "rms_sigma": 11.357790971424588,
    "rms_mond": 19.496167380503174,
    "wins_sigma": true,
    "mean_residual": -8.800538265316286,
    "inner_residual": -4.174105033791348,
    "outer_residual": -16.89679642048493,
    "residual_trend": -0.7781944557690347
  },
  {
    "name": "UGC05253",
    "V_flat": 213.0,
    "R_max": 53.29,
    "gas_fraction": 0.030824371745654066,
    "bulge_fraction": 0.7420839642975972,
    "mass_class": "massive",
    "sb_class": "HSB",
    "gas_class": "gas-poor",
    "bulge_class": "bulge-dominated",
    "fit_class": "good",
    "rms_sigma": 19.79575579528121,
    "rms_mond": 31.847289043694786,
    "wins_sigma": true,
    "mean_residual": 10.697436180756585,
    "inner_residual": 14.08067271579985,
    "outer_residual": -13.361134735106633,
    "residual_trend": -0.6437530951969122
  },
  {
    "name": "UGC05414",
    "V_flat": 56.8,
    "R_max": 4.11,
    "gas_fraction": 0.4814492112539658,
    "bulge_fraction": 0.0,
    "mass_class": "dwarf",
    "sb_class": "LSB",
    "gas_class": "mixed",
    "bulge_class": "disk-dominated",
    "fit_class": "excellent",
    "rms_sigma": 5.20488521695177,
    "rms_mond": 8.389929422889963,
    "wins_sigma": true,
    "mean_residual": 5.1333390639986,
    "inner_residual": 4.926105276356477,
    "outer_residual": 5.340572851640722,
    "residual_trend": 0.3361626981091866
  },
  {
    "name": "UGC05716",
    "V_flat": 73.0,
    "R_max": 12.37,
    "gas_fraction": 0.6947178855516268,
    "bulge_fraction": 0.0,
    "mass_class": "dwarf",
    "sb_class": "LSB",
    "gas_class": "gas-rich",
    "bulge_class": "disk-dominated",
    "fit_class": "good",
    "rms_sigma": 11.287130795417877,
    "rms_mond": 23.034579616281906,
    "wins_sigma": true,
    "mean_residual": 7.621928848663224,
    "inner_residual": 15.804857985091814,
    "outer_residual": 1.7769794654999447,
    "residual_trend": -2.2842235349306197
  },
  {
    "name": "UGC05721",
    "V_flat": 78.9,
    "R_max": 6.74,
    "gas_fraction": 0.3866272279212012,
    "bulge_fraction": 0.0,
    "mass_class": "dwarf",
    "sb_class": "HSB",
    "gas_class": "mixed",
    "bulge_class": "disk-dominated",
    "fit_class": "moderate",
    "rms_sigma": 28.842506613094383,
    "rms_mond": 32.22385237198643,
    "wins_sigma": true,
    "mean_residual": 27.259630455847727,
    "inner_residual": 28.91067611554214,
    "outer_residual": 24.16391984392067,
    "residual_trend": -0.1263913846250125
  },
  {
    "name": "UGC05750",
    "V_flat": 77.6,
    "R_max": 22.85,
    "gas_fraction": 0.6005370246507885,
    "bulge_fraction": 0.0,
    "mass_class": "dwarf",
    "sb_class": "LSB",
    "gas_class": "gas-rich",
    "bulge_class": "disk-dominated",
    "fit_class": "good",
    "rms_sigma": 11.387107173311426,
    "rms_mond": 12.335341654468507,
    "wins_sigma": true,
    "mean_residual": -5.308713082423139,
    "inner_residual": -1.674467977818753,
    "outer_residual": -21.662816053142876,
    "residual_trend": -1.4908483419443883
  },
  {
    "name": "UGC05764",
    "V_flat": 50.0,
    "R_max": 3.62,
    "gas_fraction": 0.867628189372961,
    "bulge_fraction": 0.0,
    "mass_class": "dwarf",
    "sb_class": "LSB",
    "gas_class": "gas-rich",
    "bulge_class": "disk-dominated",
    "fit_class": "good",
    "rms_sigma": 19.37429327542108,
    "rms_mond": 20.722011423936358,
    "wins_sigma": true,
    "mean_residual": 18.65916995928223,
    "inner_residual": 20.997895229888577,
    "outer_residual": 17.100019778878004,
    "residual_trend": -2.711634459519346
  },
  {
    "name": "UGC05829",
    "V_flat": 65.6,
    "R_max": 6.91,
    "gas_fraction": 0.8394887955779057,
    "bulge_fraction": 0.0,
    "mass_class": "dwarf",
    "sb_class": "LSB",
    "gas_class": "gas-rich",
    "bulge_class": "disk-dominated",
    "fit_class": "excellent",
    "rms_sigma": 7.845867500025091,
    "rms_mond": 12.55995593632337,
    "wins_sigma": true,
    "mean_residual": 4.673773348736876,
    "inner_residual": 10.710963223311298,
    "outer_residual": -0.3572182134084739,
    "residual_trend": -2.878111921336846
  },
  {
    "name": "UGC05918",
    "V_flat": 42.6,
    "R_max": 4.46,
    "gas_fraction": 0.6059308360681094,
    "bulge_fraction": 0.0,
    "mass_class": "dwarf",
    "sb_class": "LSB",
    "gas_class": "gas-rich",
    "bulge_class": "disk-dominated",
    "fit_class": "excellent",
    "rms_sigma": 9.608111398454083,
    "rms_mond": 12.759697922953235,
    "wins_sigma": true,
    "mean_residual": 8.769652693445916,
    "inner_residual": 12.33825008574415,
    "outer_residual": 6.628494258066975,
    "residual_trend": -2.413091546173096
  },
  {
    "name": "UGC05986",
    "V_flat": 109.0,
    "R_max": 9.41,
    "gas_fraction": 0.2306380203748681,
    "bulge_fraction": 0.0,
    "mass_class": "normal",
    "sb_class": "LSB",
    "gas_class": "mixed",
    "bulge_class": "disk-dominated",
    "fit_class": "moderate",
    "rms_sigma": 26.421841425875154,
    "rms_mond": 37.53366435184926,
    "wins_sigma": true,
    "mean_residual": 25.251474852666675,
    "inner_residual": 22.757078836462274,
    "outer_residual": 27.43407136684553,
    "residual_trend": 1.0440875336873587
  },
  {
    "name": "UGC05999",
    "V_flat": 97.7,
    "R_max": 16.22,
    "gas_fraction": 0.7337152300742019,
    "bulge_fraction": 0.0,
    "mass_class": "normal",
    "sb_class": "LSB",
    "gas_class": "gas-rich",
    "bulge_class": "disk-dominated",
    "fit_class": "excellent",
    "rms_sigma": 9.137773629887644,
    "rms_mond": 23.765705876175193,
    "wins_sigma": true,
    "mean_residual": -2.614791297459665,
    "inner_residual": 2.922441701665864,
    "outer_residual": -6.306279963543351,
    "residual_trend": -1.1659183986380364
  },
  {
    "name": "UGC06399",
    "V_flat": 85.6,
    "R_max": 7.85,
    "gas_fraction": 0.40573605335328544,
    "bulge_fraction": 0.0,
    "mass_class": "normal",
    "sb_class": "LSB",
    "gas_class": "mixed",
    "bulge_class": "disk-dominated",
    "fit_class": "good",
    "rms_sigma": 14.426267139011854,
    "rms_mond": 24.089523861157737,
    "wins_sigma": true,
    "mean_residual": 13.874071346154402,
    "inner_residual": 13.678577081488722,
    "outer_residual": 14.030466757886947,
    "residual_trend": 0.022363192521604815
  },
  {
    "name": "UGC06446",
    "V_flat": 83.2,
    "R_max": 10.22,
    "gas_fraction": 0.6971285001942866,
    "bulge_fraction": 0.0,
    "mass_class": "normal",
    "sb_class": "LSB",
    "gas_class": "gas-rich",
    "bulge_class": "disk-dominated",
    "fit_class": "good",
    "rms_sigma": 18.959197857233114,
    "rms_mond": 28.38647925881882,
    "wins_sigma": true,
    "mean_residual": 16.40134228695854,
    "inner_residual": 24.34166260810916,
    "outer_residual": 9.343279779269087,
    "residual_trend": -2.8022514128448424
  },
  {
    "name": "UGC06614",
    "V_flat": 204.0,
    "R_max": 64.59,
    "gas_fraction": 0.06750293494343954,
    "bulge_fraction": 0.7767732107576139,
    "mass_class": "massive",
    "sb_class": "LSB",
    "gas_class": "gas-poor",
    "bulge_class": "bulge-dominated",
    "fit_class": "moderate",
    "rms_sigma": 23.863566539992533,
    "rms_mond": 34.63979494655994,
    "wins_sigma": true,
    "mean_residual": -23.087584425084323,
    "inner_residual": -23.417027356280084,
    "outer_residual": -22.34633782989387,
    "residual_trend": -0.06595061376885282
  },
  {
    "name": "UGC06628",
    "V_flat": 42.3,
    "R_max": 7.69,
    "gas_fraction": 0.4639190071731604,
    "bulge_fraction": 0.0,
    "mass_class": "dwarf",
    "sb_class": "LSB",
    "gas_class": "mixed",
    "bulge_class": "disk-dominated",
    "fit_class": "moderate",
    "rms_sigma": 24.03606993658443,
    "rms_mond": 12.790302912237436,
    "wins_sigma": false,
    "mean_residual": -18.477784176184205,
    "inner_residual": -2.9439427494425368,
    "outer_residual": -30.128165246240457,
    "residual_trend": -6.94255958598204
  },
  {
    "name": "UGC06667",
    "V_flat": 85.0,
    "R_max": 7.85,
    "gas_fraction": 0.6955353107680597,
    "bulge_fraction": 0.0,
    "mass_class": "normal",
    "sb_class": "LSB",
    "gas_class": "gas-rich",
    "bulge_class": "disk-dominated",
    "fit_class": "moderate",
    "rms_sigma": 26.52384592057425,
    "rms_mond": 36.205746873021525,
    "wins_sigma": true,
    "mean_residual": 26.02502568259248,
    "inner_residual": 27.277547406824404,
    "outer_residual": 25.02300830320694,
    "residual_trend": -0.6744890107562777
  },
  {
    "name": "UGC06786",
    "V_flat": 215.0,
    "R_max": 34.05,
    "gas_fraction": 0.027503322132030973,
    "bulge_fraction": 0.6462033929161306,
    "mass_class": "massive",
    "sb_class": "HSB",
    "gas_class": "gas-poor",
    "bulge_class": "bulge-dominated",
    "fit_class": "poor",
    "rms_sigma": 41.54016937343747,
    "rms_mond": 59.460004509266,
    "wins_sigma": true,
    "mean_residual": 39.613375039256795,
    "inner_residual": 39.83705390045982,
    "outer_residual": 38.71865959444469,
    "residual_trend": 0.18404531700729493
  },
  {
    "name": "UGC06787",
    "V_flat": 252.0,
    "R_max": 37.19,
    "gas_fraction": 0.016724141239038925,
    "bulge_fraction": 0.8583243318777748,
    "mass_class": "massive",
    "sb_class": "HSB",
    "gas_class": "gas-poor",
    "bulge_class": "bulge-dominated",
    "fit_class": "poor",
    "rms_sigma": 35.83117630172823,
    "rms_mond": 57.89737842422843,
    "wins_sigma": true,
    "mean_residual": 25.16620815731287,
    "inner_residual": 19.687628890690224,
    "outer_residual": 45.619570752704114,
    "residual_trend": 1.6711890204537425
  },
  {
    "name": "UGC06818",
    "V_flat": 71.2,
    "R_max": 6.98,
    "gas_fraction": 0.3376184127039527,
    "bulge_fraction": 0.0,
    "mass_class": "dwarf",
    "sb_class": "LSB",
    "gas_class": "mixed",
    "bulge_class": "disk-dominated",
    "fit_class": "excellent",
    "rms_sigma": 7.072267320239828,
    "rms_mond": 15.591841183458213,
    "wins_sigma": true,
    "mean_residual": 1.4062530045066843,
    "inner_residual": -5.508316548017537,
    "outer_residual": 5.554994736021217,
    "residual_trend": 2.5337739712147087
  },
  {
    "name": "UGC06917",
    "V_flat": 110.0,
    "R_max": 10.47,
    "gas_fraction": 0.3959892415497778,
    "bulge_fraction": 0.0,
    "mass_class": "normal",
    "sb_class": "LSB",
    "gas_class": "mixed",
    "bulge_class": "disk-dominated",
    "fit_class": "good",
    "rms_sigma": 15.036498358590748,
    "rms_mond": 28.16108486428963,
    "wins_sigma": true,
    "mean_residual": 14.039139269182783,
    "inner_residual": 17.433894071610915,
    "outer_residual": 12.099279382080988,
    "residual_trend": -1.2524902525925923
  },
  {
    "name": "UGC06923",
    "V_flat": 79.3,
    "R_max": 5.16,
    "gas_fraction": 0.3766652152533343,
    "bulge_fraction": 0.0,
    "mass_class": "dwarf",
    "sb_class": "HSB",
    "gas_class": "mixed",
    "bulge_class": "disk-dominated",
    "fit_class": "excellent",
    "rms_sigma": 7.815164318963933,
    "rms_mond": 12.928192529687843,
    "wins_sigma": true,
    "mean_residual": 6.377953402247996,
    "inner_residual": 0.985764555043847,
    "outer_residual": 9.07404782585007,
    "residual_trend": 1.5630798066947498
  },
  {
    "name": "UGC06930",
    "V_flat": 108.0,
    "R_max": 16.61,
    "gas_fraction": 0.44553968214436324,
    "bulge_fraction": 0.0,
    "mass_class": "normal",
    "sb_class": "LSB",
    "gas_class": "mixed",
    "bulge_class": "disk-dominated",
    "fit_class": "good",
    "rms_sigma": 12.463060624891922,
    "rms_mond": 24.362666956888535,
    "wins_sigma": true,
    "mean_residual": 1.6876491935525337,
    "inner_residual": 14.825692033678248,
    "outer_residual": -7.071046033197942,
    "residual_trend": -2.316067381951789
  },
  {
    "name": "UGC06973",
    "V_flat": 178.0,
    "R_max": 7.85,
    "gas_fraction": 0.016070691857544957,
    "bulge_fraction": 0.18498805892656858,
    "mass_class": "massive",
    "sb_class": "HSB",
    "gas_class": "gas-poor",
    "bulge_class": "intermediate",
    "fit_class": "poor",
    "rms_sigma": 37.2695909478998,
    "rms_mond": 39.97845727248781,
    "wins_sigma": true,
    "mean_residual": -16.32145406236374,
    "inner_residual": -57.28470189130464,
    "outer_residual": 4.160169852106715,
    "residual_trend": 15.621902287481788
  },
  {
    "name": "UGC06983",
    "V_flat": 108.0,
    "R_max": 15.68,
    "gas_fraction": 0.4566570063706539,
    "bulge_fraction": 0.0,
    "mass_class": "normal",
    "sb_class": "LSB",
    "gas_class": "mixed",
    "bulge_class": "disk-dominated",
    "fit_class": "good",
    "rms_sigma": 17.345838578786807,
    "rms_mond": 34.196279016183325,
    "wins_sigma": true,
    "mean_residual": 13.11700233997039,
    "inner_residual": 23.110105936859092,
    "outer_residual": 6.121829822148297,
    "residual_trend": -2.247642440485169
  },
  {
    "name": "UGC07089",
    "V_flat": 77.6,
    "R_max": 9.16,
    "gas_fraction": 0.3506208823420584,
    "bulge_fraction": 0.0,
    "mass_class": "dwarf",
    "sb_class": "LSB",
    "gas_class": "mixed",
    "bulge_class": "disk-dominated",
    "fit_class": "excellent",
    "rms_sigma": 4.903090403979418,
    "rms_mond": 9.73380383820208,
    "wins_sigma": true,
    "mean_residual": -3.71845503020943,
    "inner_residual": -1.0001099487570777,
    "outer_residual": -5.660130088389683,
    "residual_trend": -1.049555312153514
  },
  {
    "name": "UGC07125",
    "V_flat": 65.1,
    "R_max": 18.68,
    "gas_fraction": 0.6586006347290679,
    "bulge_fraction": 0.0,
    "mass_class": "dwarf",
    "sb_class": "LSB",
    "gas_class": "gas-rich",
    "bulge_class": "disk-dominated",
    "fit_class": "moderate",
    "rms_sigma": 26.28104570162825,
    "rms_mond": 3.9158640967453437,
    "wins_sigma": false,
    "mean_residual": -22.101996002127724,
    "inner_residual": -8.540137745551489,
    "outer_residual": -33.726445936335914,
    "residual_trend": -2.5873797699662555
  },
  {
    "name": "UGC07151",
    "V_flat": 74.0,
    "R_max": 5.5,
    "gas_fraction": 0.39472410564721255,
    "bulge_fraction": 0.0,
    "mass_class": "dwarf",
    "sb_class": "HSB",
    "gas_class": "mixed",
    "bulge_class": "disk-dominated",
    "fit_class": "good",
    "rms_sigma": 11.398540762711875,
    "rms_mond": 14.348528449508517,
    "wins_sigma": true,
    "mean_residual": 10.03498235821406,
    "inner_residual": 13.497817982772494,
    "outer_residual": 7.149286004415365,
    "residual_trend": -1.8654950909060233
  },
  {
    "name": "UGC07261",
    "V_flat": 74.7,
    "R_max": 6.67,
    "gas_fraction": 0.3987830630834127,
    "bulge_fraction": 0.0,
    "mass_class": "dwarf",
    "sb_class": "LSB",
    "gas_class": "mixed",
    "bulge_class": "disk-dominated",
    "fit_class": "good",
    "rms_sigma": 13.765313368744028,
    "rms_mond": 19.154135965585695,
    "wins_sigma": true,
    "mean_residual": 12.51315951376221,
    "inner_residual": 17.899053548027826,
    "outer_residual": 8.473738988063,
    "residual_trend": -2.9346890658673233
  },
  {
    "name": "UGC07323",
    "V_flat": 82.8,
    "R_max": 5.82,
    "gas_fraction": 0.3015096787484977,
    "bulge_fraction": 0.0,
    "mass_class": "normal",
    "sb_class": "LSB",
    "gas_class": "mixed",
    "bulge_class": "disk-dominated",
    "fit_class": "excellent",
    "rms_sigma": 4.757390463611374,
    "rms_mond": 10.081378707141681,
    "wins_sigma": true,
    "mean_residual": 4.517665812069862,
    "inner_residual": 4.471839253939477,
    "outer_residual": 4.548216850823452,
    "residual_trend": -0.20482087752635073
  },
  {
    "name": "UGC07399",
    "V_flat": 103.0,
    "R_max": 6.13,
    "gas_fraction": 0.461898638118874,
    "bulge_fraction": 0.0,
    "mass_class": "normal",
    "sb_class": "LSB",
    "gas_class": "mixed",
    "bulge_class": "disk-dominated",
    "fit_class": "poor",
    "rms_sigma": 39.834693120886065,
    "rms_mond": 45.880585162958155,
    "wins_sigma": true,
    "mean_residual": 39.36310107866772,
    "inner_residual": 36.586522085649506,
    "outer_residual": 41.214153740679855,
    "residual_trend": 1.7006251807041306
  },
  {
    "name": "UGC07524",
    "V_flat": 82.3,
    "R_max": 10.69,
    "gas_fraction": 0.6114639664360593,
    "bulge_fraction": 0.0,
    "mass_class": "normal",
    "sb_class": "LSB",
    "gas_class": "gas-rich",
    "bulge_class": "disk-dominated",
    "fit_class": "excellent",
    "rms_sigma": 9.644698905564532,
    "rms_mond": 18.882236075068494,
    "wins_sigma": true,
    "mean_residual": 5.568068502060397,
    "inner_residual": 11.310956790991517,
    "outer_residual": 0.18411073118747634,
    "residual_trend": -2.0548196986397445
  },
  {
    "name": "UGC07559",
    "V_flat": 31.1,
    "R_max": 2.53,
    "gas_fraction": 0.6436471766187453,
    "bulge_fraction": 0.0,
    "mass_class": "dwarf",
    "sb_class": "LSB",
    "gas_class": "gas-rich",
    "bulge_class": "disk-dominated",
    "fit_class": "excellent",
    "rms_sigma": 2.10455843005244,
    "rms_mond": 2.6231077388946273,
    "wins_sigma": true,
    "mean_residual": 1.4539939415807337,
    "inner_residual": 1.1308454662151128,
    "outer_residual": 1.6963552981049492,
    "residual_trend": -0.29575315128893054
  },
  {
    "name": "UGC07577",
    "V_flat": 15.9,
    "R_max": 1.69,
    "gas_fraction": 0.4937449615983264,
    "bulge_fraction": 0.0,
    "mass_class": "dwarf",
    "sb_class": "LSB",
    "gas_class": "mixed",
    "bulge_class": "disk-dominated",
    "fit_class": "excellent",
    "rms_sigma": 3.2649339597928826,
    "rms_mond": 3.993883193863302,
    "wins_sigma": true,
    "mean_residual": -2.523719392205126,
    "inner_residual": -0.6823858435503294,
    "outer_residual": -3.9967862311289637,
    "residual_trend": -3.5603181118797873
  },
  {
    "name": "UGC07603",
    "V_flat": 63.0,
    "R_max": 4.11,
    "gas_fraction": 0.38442038620334656,
    "bulge_fraction": 0.0,
    "mass_class": "dwarf",
    "sb_class": "HSB",
    "gas_class": "mixed",
    "bulge_class": "disk-dominated",
    "fit_class": "good",
    "rms_sigma": 18.49767565656992,
    "rms_mond": 21.29747325894121,
    "wins_sigma": true,
    "mean_residual": 17.673907085477,
    "inner_residual": 14.879705890052769,
    "outer_residual": 20.468108280901237,
    "residual_trend": 3.301512519616855
  },
  {
    "name": "UGC07608",
    "V_flat": 66.0,
    "R_max": 4.78,
    "gas_fraction": 0.8016017860330381,
    "bulge_fraction": 0.0,
    "mass_class": "dwarf",
    "sb_class": "LSB",
    "gas_class": "gas-rich",
    "bulge_class": "disk-dominated",
    "fit_class": "good",
    "rms_sigma": 18.207346624208927,
    "rms_mond": 23.14845101493665,
    "wins_sigma": true,
    "mean_residual": 17.350795828100708,
    "inner_residual": 15.003225472872582,
    "outer_residual": 19.69836618332883,
    "residual_trend": 2.4112942007929696
  },
  {
    "name": "UGC07690",
    "V_flat": 56.9,
    "R_max": 4.13,
    "gas_fraction": 0.2958512743797357,
    "bulge_fraction": 0.0,
    "mass_class": "dwarf",
    "sb_class": "HSB",
    "gas_class": "mixed",
    "bulge_class": "disk-dominated",
    "fit_class": "good",
    "rms_sigma": 11.34678700881762,
    "rms_mond": 11.550230132694619,
    "wins_sigma": true,
    "mean_residual": 9.940141396206746,
    "inner_residual": 15.071791485562331,
    "outer_residual": 6.09140382919006,
    "residual_trend": -3.832712172358729
  },
  {
    "name": "UGC07866",
    "V_flat": 30.6,
    "R_max": 2.32,
    "gas_fraction": 0.573183342875444,
    "bulge_fraction": 0.0,
    "mass_class": "dwarf",
    "sb_class": "LSB",
    "gas_class": "gas-rich",
    "bulge_class": "disk-dominated",
    "fit_class": "excellent",
    "rms_sigma": 4.2550197445297435,
    "rms_mond": 3.5804829639135374,
    "wins_sigma": false,
    "mean_residual": 3.94668781511545,
    "inner_residual": 5.409385479843149,
    "outer_residual": 2.8496645665696763,
    "residual_trend": -1.7695417966912614
  },
  {
    "name": "UGC08286",
    "V_flat": 83.8,
    "R_max": 8.04,
    "gas_fraction": 0.4597348347788681,
    "bulge_fraction": 0.0,
    "mass_class": "normal",
    "sb_class": "LSB",
    "gas_class": "mixed",
    "bulge_class": "disk-dominated",
    "fit_class": "moderate",
    "rms_sigma": 22.585492513249978,
    "rms_mond": 30.77651415473185,
    "wins_sigma": true,
    "mean_residual": 21.644978856577765,
    "inner_residual": 25.605313598532256,
    "outer_residual": 18.12468130817378,
    "residual_trend": -1.434290555133593
  },
  {
    "name": "UGC08490",
    "V_flat": 77.6,
    "R_max": 10.15,
    "gas_fraction": 0.369477489449883,
    "bulge_fraction": 0.0,
    "mass_class": "dwarf",
    "sb_class": "LSB",
    "gas_class": "mixed",
    "bulge_class": "disk-dominated",
    "fit_class": "good",
    "rms_sigma": 19.88529383135207,
    "rms_mond": 30.1890283861819,
    "wins_sigma": true,
    "mean_residual": 18.91426136870654,
    "inner_residual": 23.974031559992714,
    "outer_residual": 14.486962451331129,
    "residual_trend": -1.8086459829281982
  },
  {
    "name": "UGC08550",
    "V_flat": 57.5,
    "R_max": 5.36,
    "gas_fraction": 0.5375516658364278,
    "bulge_fraction": 0.0,
    "mass_class": "dwarf",
    "sb_class": "LSB",
    "gas_class": "gas-rich",
    "bulge_class": "disk-dominated",
    "fit_class": "good",
    "rms_sigma": 14.298915164043638,
    "rms_mond": 18.71372493200981,
    "wins_sigma": true,
    "mean_residual": 13.788659830984313,
    "inner_residual": 15.469133608067088,
    "outer_residual": 12.388265016748674,
    "residual_trend": -1.4598141935133155
  },
  {
    "name": "UGC08699",
    "V_flat": 182.0,
    "R_max": 25.7,
    "gas_fraction": 0.02758924497693918,
    "bulge_fraction": 0.7924422739299292,
    "mass_class": "massive",
    "sb_class": "HSB",
    "gas_class": "gas-poor",
    "bulge_class": "bulge-dominated",
    "fit_class": "moderate",
    "rms_sigma": 22.878293464684674,
    "rms_mond": 36.735642183852754,
    "wins_sigma": true,
    "mean_residual": 16.840901781526345,
    "inner_residual": 17.814129799375223,
    "outer_residual": 12.113794266260376,
    "residual_trend": 0.4401340983502307
  },
  {
    "name": "UGC08837",
    "V_flat": 46.6,
    "R_max": 4.2,
    "gas_fraction": 0.5762880844661228,
    "bulge_fraction": 0.0,
    "mass_class": "dwarf",
    "sb_class": "LSB",
    "gas_class": "gas-rich",
    "bulge_class": "disk-dominated",
    "fit_class": "excellent",
    "rms_sigma": 2.7316694643965325,
    "rms_mond": 3.7262749051300976,
    "wins_sigma": true,
    "mean_residual": -2.333584721762467,
    "inner_residual": -2.269536967825376,
    "outer_residual": -2.3976324756995577,
    "residual_trend": -0.25537908362465417
  },
  {
    "name": "UGC09037",
    "V_flat": 150.0,
    "R_max": 27.96,
    "gas_fraction": 0.2629537933415577,
    "bulge_fraction": 0.0,
    "mass_class": "massive",
    "sb_class": "LSB",
    "gas_class": "mixed",
    "bulge_class": "disk-dominated",
    "fit_class": "poor",
    "rms_sigma": 30.94788232593043,
    "rms_mond": 17.113436893962273,
    "wins_sigma": false,
    "mean_residual": -29.847653498006604,
    "inner_residual": -26.3722101565992,
    "outer_residual": -32.74385628251277,
    "residual_trend": -0.5677299557450431
  },
  {
    "name": "UGC09133",
    "V_flat": 227.0,
    "R_max": 108.31,
    "gas_fraction": 0.027990115197181475,
    "bulge_fraction": 0.6918549352877806,
    "mass_class": "massive",
    "sb_class": "HSB",
    "gas_class": "gas-poor",
    "bulge_class": "bulge-dominated",
    "fit_class": "poor",
    "rms_sigma": 30.86182700263218,
    "rms_mond": 45.96301847774913,
    "wins_sigma": true,
    "mean_residual": -1.5440748780882079,
    "inner_residual": 11.047599688488344,
    "outer_residual": -39.31909857781786,
    "residual_trend": -0.8104599451871128
  },
  {
    "name": "UGC09992",
    "V_flat": 33.4,
    "R_max": 3.89,
    "gas_fraction": 0.5274985954179412,
    "bulge_fraction": 0.0,
    "mass_class": "dwarf",
    "sb_class": "LSB",
    "gas_class": "gas-rich",
    "bulge_class": "disk-dominated",
    "fit_class": "excellent",
    "rms_sigma": 6.980763138577952,
    "rms_mond": 3.2508271209246598,
    "wins_sigma": false,
    "mean_residual": -1.2217953142648448,
    "inner_residual": 6.24549695865929,
    "outer_residual": -6.199990162880934,
    "residual_trend": -6.201368979008116
  },
  {
    "name": "UGC10310",
    "V_flat": 72.4,
    "R_max": 7.74,
    "gas_fraction": 0.5492167200687283,
    "bulge_fraction": 0.0,
    "mass_class": "dwarf",
    "sb_class": "LSB",
    "gas_class": "gas-rich",
    "bulge_class": "disk-dominated",
    "fit_class": "good",
    "rms_sigma": 11.326172603260042,
    "rms_mond": 16.930485561247956,
    "wins_sigma": true,
    "mean_residual": 7.543030925970024,
    "inner_residual": 15.283970540130795,
    "outer_residual": 1.7373262153494462,
    "residual_trend": -3.3896538556551747
  },
  {
    "name": "UGC11455",
    "V_flat": 272.0,
    "R_max": 41.93,
    "gas_fraction": 0.055340533735708436,
    "bulge_fraction": 0.0,
    "mass_class": "massive",
    "sb_class": "HSB",
    "gas_class": "gas-poor",
    "bulge_class": "disk-dominated",
    "fit_class": "good",
    "rms_sigma": 15.003716207036518,
    "rms_mond": 31.48649423119175,
    "wins_sigma": true,
    "mean_residual": 2.6133902770753075,
    "inner_residual": 8.10211684847047,
    "outer_residual": -11.65729880855211,
    "residual_trend": -0.5053588718968054
  },
  {
    "name": "UGC11557",
    "V_flat": 81.6,
    "R_max": 10.56,
    "gas_fraction": 0.22160378503519862,
    "bulge_fraction": 0.0,
    "mass_class": "normal",
    "sb_class": "HSB",
    "gas_class": "mixed",
    "bulge_class": "disk-dominated",
    "fit_class": "moderate",
    "rms_sigma": 21.631929328734078,
    "rms_mond": 14.71233020973973,
    "wins_sigma": false,
    "mean_residual": -20.666484801997324,
    "inner_residual": -17.67739845060029,
    "outer_residual": -24.85120569395317,
    "residual_trend": -1.6687408943452613
  },
  {
    "name": "UGC11820",
    "V_flat": 81.25,
    "R_max": 15.82,
    "gas_fraction": 0.7817033010034585,
    "bulge_fraction": 0.0,
    "mass_class": "normal",
    "sb_class": "LSB",
    "gas_class": "gas-rich",
    "bulge_class": "disk-dominated",
    "fit_class": "good",
    "rms_sigma": 11.771644983743593,
    "rms_mond": 16.431566357206062,
    "wins_sigma": true,
    "mean_residual": 3.9717585127646897,
    "inner_residual": 12.135050411777549,
    "outer_residual": -8.273179335754598,
    "residual_trend": -1.803387362533844
  },
  {
    "name": "UGC11914",
    "V_flat": 297.0,
    "R_max": 9.83,
    "gas_fraction": 0.012569467336526354,
    "bulge_fraction": 0.582819066620096,
    "mass_class": "massive",
    "sb_class": "HSB",
    "gas_class": "gas-poor",
    "bulge_class": "bulge-dominated",
    "fit_class": "poor",
    "rms_sigma": 46.170890270897175,
    "rms_mond": 44.227626377994035,
    "wins_sigma": false,
    "mean_residual": 44.39178919393676,
    "inner_residual": 41.27814102836467,
    "outer_residual": 50.07758149628578,
    "residual_trend": 3.388862875108752
  },
  {
    "name": "UGC12506",
    "V_flat": 226.0,
    "R_max": 49.99,
    "gas_fraction": 0.30534469347702636,
    "bulge_fraction": 0.0,
    "mass_class": "massive",
    "sb_class": "LSB",
    "gas_class": "mixed",
    "bulge_class": "disk-dominated",
    "fit_class": "poor",
    "rms_sigma": 45.46566100786989,
    "rms_mond": 79.88974687821595,
    "wins_sigma": true,
    "mean_residual": 32.22937595330943,
    "inner_residual": 59.85667397228843,
    "outer_residual": 6.328784060516609,
    "residual_trend": -2.1623370978526393
  },
  {
    "name": "UGC12632",
    "V_flat": 73.1,
    "R_max": 10.66,
    "gas_fraction": 0.675894850428886,
    "bulge_fraction": 0.0,
    "mass_class": "dwarf",
    "sb_class": "LSB",
    "gas_class": "gas-rich",
    "bulge_class": "disk-dominated",
    "fit_class": "good",
    "rms_sigma": 11.081877777524786,
    "rms_mond": 19.78339467656957,
    "wins_sigma": true,
    "mean_residual": 6.372192729536041,
    "inner_residual": 14.255637828656091,
    "outer_residual": -0.5258217321940011,
    "residual_trend": -2.638039952718333
  },
  {
    "name": "UGC12732",
    "V_flat": 95.5,
    "R_max": 15.4,
    "gas_fraction": 0.7520736367437538,
    "bulge_fraction": 0.0,
    "mass_class": "normal",
    "sb_class": "LSB",
    "gas_class": "gas-rich",
    "bulge_class": "disk-dominated",
    "fit_class": "good",
    "rms_sigma": 12.643059141251785,
    "rms_mond": 26.898261959268318,
    "wins_sigma": true,
    "mean_residual": 7.5715830400580595,
    "inner_residual": 16.40913368786229,
    "outer_residual": -1.2659676077461715,
    "residual_trend": -2.185950730432665
  },
  {
    "name": "UGCA281",
    "V_flat": 28.8,
    "R_max": 1.08,
    "gas_fraction": 0.3895815424069972,
    "bulge_fraction": 0.0,
    "mass_class": "dwarf",
    "sb_class": "HSB",
    "gas_class": "mixed",
    "bulge_class": "disk-dominated",
    "fit_class": "excellent",
    "rms_sigma": 7.527511840982092,
    "rms_mond": 4.956128961694725,
    "wins_sigma": false,
    "mean_residual": 7.25049274460303,
    "inner_residual": 5.114156723737812,
    "outer_residual": 8.852744760251944,
    "residual_trend": 5.478311064068628
  },
  {
    "name": "UGCA442",
    "V_flat": 56.5,
    "R_max": 6.33,
    "gas_fraction": 0.8491925736474458,
    "bulge_fraction": 0.0,
    "mass_class": "dwarf",
    "sb_class": "LSB",
    "gas_class": "gas-rich",
    "bulge_class": "disk-dominated",
    "fit_class": "excellent",
    "rms_sigma": 8.912165778836442,
    "rms_mond": 16.569008293101913,
    "wins_sigma": true,
    "mean_residual": 8.794519722772364,
    "inner_residual": 7.482658276416406,
    "outer_residual": 10.106381169128321,
    "residual_trend": 0.6935866456677707
  },
  {
    "name": "UGCA444",
    "V_flat": 37.6,
    "R_max": 2.62,
    "gas_fraction": 0.9424626225783895,
    "bulge_fraction": 0.0,
    "mass_class": "dwarf",
    "sb_class": "LSB",
    "gas_class": "gas-rich",
    "bulge_class": "disk-dominated",
    "fit_class": "excellent",
    "rms_sigma": 6.916387726496129,
    "rms_mond": 7.293381964627087,
    "wins_sigma": true,
    "mean_residual": 6.7992103708498846,
    "inner_residual": 6.51833258716884,
    "outer_residual": 7.050522072038188,
    "residual_trend": 0.6625226357810381
  }
]